{
"meta":{"test_sets":[],"test_metrics":[],"learn_metrics":[{"best_value":"Min","name":"RMSE"}],"launch_mode":"Train","parameters":"","iteration_count":1000,"learn_sets":["learn"],"name":"experiment"},
"iterations":[
{"learn":[96.94811759],"iteration":0,"passed_time":0.1603456961,"remaining_time":160.1853504},
{"learn":[94.32509346],"iteration":1,"passed_time":0.1725382051,"remaining_time":86.09656435},
{"learn":[91.9274101],"iteration":2,"passed_time":0.1849847479,"remaining_time":61.47659788},
{"learn":[89.81741012],"iteration":3,"passed_time":0.1989401502,"remaining_time":49.5360974},
{"learn":[87.91911401],"iteration":4,"passed_time":0.212281011,"remaining_time":42.2439212},
{"learn":[86.25163439],"iteration":5,"passed_time":0.2247239078,"remaining_time":37.22926073},
{"learn":[84.66877541],"iteration":6,"passed_time":0.2360219824,"remaining_time":33.48140408},
{"learn":[83.3279429],"iteration":7,"passed_time":0.2475006453,"remaining_time":30.69008001},
{"learn":[82.06991881],"iteration":8,"passed_time":0.2587934389,"remaining_time":28.4960331},
{"learn":[80.86791726],"iteration":9,"passed_time":0.2689731219,"remaining_time":26.62833907},
{"learn":[79.8388676],"iteration":10,"passed_time":0.2794943676,"remaining_time":25.12908451},
{"learn":[78.9477515],"iteration":11,"passed_time":0.2899298516,"remaining_time":23.87089111},
{"learn":[78.10818514],"iteration":12,"passed_time":0.3019238045,"remaining_time":22.92298423},
{"learn":[77.17890633],"iteration":13,"passed_time":0.3143278279,"remaining_time":22.13765988},
{"learn":[76.46534812],"iteration":14,"passed_time":0.3236199425,"remaining_time":21.25104289},
{"learn":[75.84229756],"iteration":15,"passed_time":0.3314448073,"remaining_time":20.38385565},
{"learn":[75.04507812],"iteration":16,"passed_time":0.3392445167,"remaining_time":19.61631529},
{"learn":[74.34826077],"iteration":17,"passed_time":0.3464197051,"remaining_time":18.89911947},
{"learn":[73.83119759],"iteration":18,"passed_time":0.3537198567,"remaining_time":18.26311471},
{"learn":[73.24672414],"iteration":19,"passed_time":0.3616763547,"remaining_time":17.72214138},
{"learn":[72.67168131],"iteration":20,"passed_time":0.3712957123,"remaining_time":17.30945249},
{"learn":[72.25514299],"iteration":21,"passed_time":0.3817121452,"remaining_time":16.96883991},
{"learn":[71.79126561],"iteration":22,"passed_time":0.3921601767,"remaining_time":16.65828229},
{"learn":[71.39164727],"iteration":23,"passed_time":0.4012652697,"remaining_time":16.31812097},
{"learn":[71.02243103],"iteration":24,"passed_time":0.412592818,"remaining_time":16.0911199},
{"learn":[70.67849329],"iteration":25,"passed_time":0.4203243635,"remaining_time":15.74599731},
{"learn":[70.36969761],"iteration":26,"passed_time":0.4280697863,"remaining_time":15.42636674},
{"learn":[70.04052899],"iteration":27,"passed_time":0.4339810841,"remaining_time":15.06534335},
{"learn":[69.74314774],"iteration":28,"passed_time":0.4421884205,"remaining_time":14.80568815},
{"learn":[69.49011346],"iteration":29,"passed_time":0.4479906652,"remaining_time":14.48503151},
{"learn":[69.19380018],"iteration":30,"passed_time":0.456166154,"remaining_time":14.25887107},
{"learn":[68.99400811],"iteration":31,"passed_time":0.4630631965,"remaining_time":14.00766169},
{"learn":[68.72660502],"iteration":32,"passed_time":0.4699908089,"remaining_time":13.77215491},
{"learn":[68.4653298],"iteration":33,"passed_time":0.4773493681,"remaining_time":13.56233793},
{"learn":[68.20812961],"iteration":34,"passed_time":0.4847904481,"remaining_time":13.36636521},
{"learn":[68.04516876],"iteration":35,"passed_time":0.4917574871,"remaining_time":13.16817271},
{"learn":[67.84902946],"iteration":36,"passed_time":0.4979570668,"remaining_time":12.96034203},
{"learn":[67.65622892],"iteration":37,"passed_time":0.5052159316,"remaining_time":12.78994016},
{"learn":[67.46481526],"iteration":38,"passed_time":0.5110840389,"remaining_time":12.59363491},
{"learn":[67.3215842],"iteration":39,"passed_time":0.5188484107,"remaining_time":12.45236186},
{"learn":[67.12160837],"iteration":40,"passed_time":0.5251502309,"remaining_time":12.28339199},
{"learn":[66.97266975],"iteration":41,"passed_time":0.5324814441,"remaining_time":12.14564818},
{"learn":[66.79767907],"iteration":42,"passed_time":0.5395370122,"remaining_time":12.00783537},
{"learn":[66.64084201],"iteration":43,"passed_time":0.5452440622,"remaining_time":11.84666644},
{"learn":[66.5301607],"iteration":44,"passed_time":0.552453381,"remaining_time":11.72428842},
{"learn":[66.42341475],"iteration":45,"passed_time":0.5575805703,"remaining_time":11.56373618},
{"learn":[66.31044194],"iteration":46,"passed_time":0.5652709792,"remaining_time":11.46177113},
{"learn":[66.19733422],"iteration":47,"passed_time":0.5717195877,"remaining_time":11.33910516},
{"learn":[66.06103722],"iteration":48,"passed_time":0.5783802272,"remaining_time":11.22529788},
{"learn":[65.92656926],"iteration":49,"passed_time":0.5856240427,"remaining_time":11.12685681},
{"learn":[65.81801514],"iteration":50,"passed_time":0.5923025832,"remaining_time":11.02147356},
{"learn":[65.73804991],"iteration":51,"passed_time":0.5997223384,"remaining_time":10.93339955},
{"learn":[65.65566655],"iteration":52,"passed_time":0.6052427489,"remaining_time":10.81443176},
{"learn":[65.56902858],"iteration":53,"passed_time":0.611490665,"remaining_time":10.71241054},
{"learn":[65.47455439],"iteration":54,"passed_time":0.6175857023,"remaining_time":10.61124525},
{"learn":[65.38916807],"iteration":55,"passed_time":0.6231812452,"remaining_time":10.50505528},
{"learn":[65.27436302],"iteration":56,"passed_time":0.6294597221,"remaining_time":10.4136933},
{"learn":[65.16794287],"iteration":57,"passed_time":0.635232524,"remaining_time":10.31705237},
{"learn":[65.07216334],"iteration":58,"passed_time":0.6410399825,"remaining_time":10.22404447},
{"learn":[65.00544457],"iteration":59,"passed_time":0.6484392457,"remaining_time":10.15888152},
{"learn":[64.92916319],"iteration":60,"passed_time":0.6541974238,"remaining_time":10.07035051},
{"learn":[64.85230673],"iteration":61,"passed_time":0.6601886723,"remaining_time":9.98801572},
{"learn":[64.77243915],"iteration":62,"passed_time":0.6658322135,"remaining_time":9.902933081},
{"learn":[64.71235924],"iteration":63,"passed_time":0.6711812145,"remaining_time":9.816025262},
{"learn":[64.59759339],"iteration":64,"passed_time":0.6772669104,"remaining_time":9.742224019},
{"learn":[64.54520126],"iteration":65,"passed_time":0.6831716975,"remaining_time":9.667914629},
{"learn":[64.44076333],"iteration":66,"passed_time":0.6885433655,"remaining_time":9.588223283},
{"learn":[64.3844439],"iteration":67,"passed_time":0.6945047711,"remaining_time":9.518800686},
{"learn":[64.32742885],"iteration":68,"passed_time":0.7001689659,"remaining_time":9.447207352},
{"learn":[64.2439841],"iteration":69,"passed_time":0.7063933379,"remaining_time":9.384940061},
{"learn":[64.17557877],"iteration":70,"passed_time":0.7117697035,"remaining_time":9.313155698},
{"learn":[64.10269528],"iteration":71,"passed_time":0.7175901188,"remaining_time":9.248939309},
{"learn":[64.04558346],"iteration":72,"passed_time":0.7237141457,"remaining_time":9.190178262},
{"learn":[63.98925052],"iteration":73,"passed_time":0.729387786,"remaining_time":9.127203917},
{"learn":[63.92580469],"iteration":74,"passed_time":0.735453153,"remaining_time":9.070588888},
{"learn":[63.88267304],"iteration":75,"passed_time":0.7417938428,"remaining_time":9.018651457},
{"learn":[63.83257123],"iteration":76,"passed_time":0.7490061898,"remaining_time":8.978346925},
{"learn":[63.7896465],"iteration":77,"passed_time":0.7561140022,"remaining_time":8.937655256},
{"learn":[63.73679554],"iteration":78,"passed_time":0.7625888888,"remaining_time":8.89043502},
{"learn":[63.69500922],"iteration":79,"passed_time":0.7704282581,"remaining_time":8.859924968},
{"learn":[63.6432814],"iteration":80,"passed_time":0.777663202,"remaining_time":8.82311707},
{"learn":[63.59516028],"iteration":81,"passed_time":0.7844782332,"remaining_time":8.782329489},
{"learn":[63.53577269],"iteration":82,"passed_time":0.7907133088,"remaining_time":8.735953063},
{"learn":[63.49492655],"iteration":83,"passed_time":0.79785342,"remaining_time":8.70040158},
{"learn":[63.45227754],"iteration":84,"passed_time":0.8051790355,"remaining_time":8.6675155},
{"learn":[63.41091173],"iteration":85,"passed_time":0.8125465575,"remaining_time":8.635669227},
{"learn":[63.36102106],"iteration":86,"passed_time":0.8210487117,"remaining_time":8.616292803},
{"learn":[63.32231656],"iteration":87,"passed_time":0.8292870292,"remaining_time":8.594429211},
{"learn":[63.2839534],"iteration":88,"passed_time":0.8384058865,"remaining_time":8.581884973},
{"learn":[63.25437312],"iteration":89,"passed_time":0.8472429744,"remaining_time":8.566567852},
{"learn":[63.20942217],"iteration":90,"passed_time":0.8573797132,"remaining_time":8.564375377},
{"learn":[63.17500638],"iteration":91,"passed_time":0.8713596321,"remaining_time":8.599940717},
{"learn":[63.14773997],"iteration":92,"passed_time":0.8811977927,"remaining_time":8.59404729},
{"learn":[63.11519674],"iteration":93,"passed_time":0.8939211887,"remaining_time":8.615878691},
{"learn":[63.06984404],"iteration":94,"passed_time":0.9063353692,"remaining_time":8.634036938},
{"learn":[63.0281167],"iteration":95,"passed_time":0.9177750346,"remaining_time":8.642381576},
{"learn":[62.97872071],"iteration":96,"passed_time":0.9286213489,"remaining_time":8.644794619},
{"learn":[62.94083936],"iteration":97,"passed_time":0.9403571223,"remaining_time":8.655123718},
{"learn":[62.89801656],"iteration":98,"passed_time":0.9508250449,"remaining_time":8.653468338},
{"learn":[62.86877231],"iteration":99,"passed_time":0.959627679,"remaining_time":8.636649111},
{"learn":[62.82364171],"iteration":100,"passed_time":0.968557346,"remaining_time":8.621119347},
{"learn":[62.78772599],"iteration":101,"passed_time":0.975455164,"remaining_time":8.587830758},
{"learn":[62.75887073],"iteration":102,"passed_time":0.9826103374,"remaining_time":8.557295851},
{"learn":[62.7289451],"iteration":103,"passed_time":0.9890022587,"remaining_time":8.520634844},
{"learn":[62.70759947],"iteration":104,"passed_time":0.9955384896,"remaining_time":8.485780459},
{"learn":[62.67819446],"iteration":105,"passed_time":1.002026005,"remaining_time":8.451049513},
{"learn":[62.65080114],"iteration":106,"passed_time":1.008205909,"remaining_time":8.414279219},
{"learn":[62.62736625],"iteration":107,"passed_time":1.014668274,"remaining_time":8.380408341},
{"learn":[62.5935148],"iteration":108,"passed_time":1.020702505,"remaining_time":8.34354066},
{"learn":[62.55880333],"iteration":109,"passed_time":1.02676051,"remaining_time":8.307425941},
{"learn":[62.52064432],"iteration":110,"passed_time":1.033054822,"remaining_time":8.273745378},
{"learn":[62.49573024],"iteration":111,"passed_time":1.038828005,"remaining_time":8.236422038},
{"learn":[62.47348285],"iteration":112,"passed_time":1.044738335,"remaining_time":8.200733654},
{"learn":[62.4538766],"iteration":113,"passed_time":1.051178875,"remaining_time":8.169688452},
{"learn":[62.39427143],"iteration":114,"passed_time":1.056844348,"remaining_time":8.133106508},
{"learn":[62.33558085],"iteration":115,"passed_time":1.062971462,"remaining_time":8.100575623},
{"learn":[62.29674435],"iteration":116,"passed_time":1.06890379,"remaining_time":8.067026036},
{"learn":[62.25802963],"iteration":117,"passed_time":1.074400912,"remaining_time":8.030691563},
{"learn":[62.22933281],"iteration":118,"passed_time":1.079940294,"remaining_time":7.995188227},
{"learn":[62.18952245],"iteration":119,"passed_time":1.085417354,"remaining_time":7.959727261},
{"learn":[62.16049385],"iteration":120,"passed_time":1.09170819,"remaining_time":7.930673547},
{"learn":[62.12993636],"iteration":121,"passed_time":1.098380288,"remaining_time":7.90473683},
{"learn":[62.11035546],"iteration":122,"passed_time":1.10379685,"remaining_time":7.870161277},
{"learn":[62.07020012],"iteration":123,"passed_time":1.109443996,"remaining_time":7.837685005},
{"learn":[62.03995909],"iteration":124,"passed_time":1.115109363,"remaining_time":7.80576554},
{"learn":[62.02023251],"iteration":125,"passed_time":1.120842675,"remaining_time":7.774734109},
{"learn":[61.99487886],"iteration":126,"passed_time":1.126339797,"remaining_time":7.742477504},
{"learn":[61.96019558],"iteration":127,"passed_time":1.132237913,"remaining_time":7.713370785},
{"learn":[61.93750883],"iteration":128,"passed_time":1.138261402,"remaining_time":7.685470398},
{"learn":[61.88781263],"iteration":129,"passed_time":1.144187071,"remaining_time":7.65725194},
{"learn":[61.87493326],"iteration":130,"passed_time":1.149761282,"remaining_time":7.627042394},
{"learn":[61.84826166],"iteration":131,"passed_time":1.155412475,"remaining_time":7.597712337},
{"learn":[61.82517147],"iteration":132,"passed_time":1.162221657,"remaining_time":7.576287041},
{"learn":[61.79811423],"iteration":133,"passed_time":1.168373623,"remaining_time":7.550832517},
{"learn":[61.77994964],"iteration":134,"passed_time":1.174454427,"remaining_time":7.525207997},
{"learn":[61.76014197],"iteration":135,"passed_time":1.18317383,"remaining_time":7.516633746},
{"learn":[61.73945389],"iteration":136,"passed_time":1.188957503,"remaining_time":7.489564416},
{"learn":[61.71340819],"iteration":137,"passed_time":1.195977433,"remaining_time":7.470525707},
{"learn":[61.68559019],"iteration":138,"passed_time":1.203511111,"remaining_time":7.454842203},
{"learn":[61.66561833],"iteration":139,"passed_time":1.211011865,"remaining_time":7.439072885},
{"learn":[61.64231684],"iteration":140,"passed_time":1.21782299,"remaining_time":7.419219491},
{"learn":[61.62034163],"iteration":141,"passed_time":1.224210624,"remaining_time":7.396990955},
{"learn":[61.60768604],"iteration":142,"passed_time":1.230257283,"remaining_time":7.372940498},
{"learn":[61.58648978],"iteration":143,"passed_time":1.237231115,"remaining_time":7.354651628},
{"learn":[61.56165804],"iteration":144,"passed_time":1.245547372,"remaining_time":7.344434503},
{"learn":[61.53811125],"iteration":145,"passed_time":1.25206024,"remaining_time":7.323694828},
{"learn":[61.51525985],"iteration":146,"passed_time":1.258147515,"remaining_time":7.300679116},
{"learn":[61.4996731],"iteration":147,"passed_time":1.264342167,"remaining_time":7.278510311},
{"learn":[61.48020723],"iteration":148,"passed_time":1.270420815,"remaining_time":7.255893382},
{"learn":[61.45275379],"iteration":149,"passed_time":1.276387998,"remaining_time":7.232865323},
{"learn":[61.42429956],"iteration":150,"passed_time":1.282324367,"remaining_time":7.209889982},
{"learn":[61.40569288],"iteration":151,"passed_time":1.288221147,"remaining_time":7.186917978},
{"learn":[61.38866946],"iteration":152,"passed_time":1.294249465,"remaining_time":7.164897365},
{"learn":[61.36482256],"iteration":153,"passed_time":1.300863331,"remaining_time":7.146301154},
{"learn":[61.34532764],"iteration":154,"passed_time":1.306409451,"remaining_time":7.12203862},
{"learn":[61.31890504],"iteration":155,"passed_time":1.31195688,"remaining_time":7.098023122},
{"learn":[61.29789966],"iteration":156,"passed_time":1.317724721,"remaining_time":7.07542637},
{"learn":[61.28118039],"iteration":157,"passed_time":1.323342598,"remaining_time":7.052243467},
{"learn":[61.25221859],"iteration":158,"passed_time":1.328900991,"remaining_time":7.028966875},
{"learn":[61.22453399],"iteration":159,"passed_time":1.334403597,"remaining_time":7.005618883},
{"learn":[61.20812081],"iteration":160,"passed_time":1.340184152,"remaining_time":6.983941015},
{"learn":[61.18325688],"iteration":161,"passed_time":1.345941684,"remaining_time":6.962340317},
{"learn":[61.17176012],"iteration":162,"passed_time":1.351572458,"remaining_time":6.940283114},
{"learn":[61.1541311],"iteration":163,"passed_time":1.357593531,"remaining_time":6.920415806},
{"learn":[61.13600885],"iteration":164,"passed_time":1.363361489,"remaining_time":6.899435414},
{"learn":[61.10548873],"iteration":165,"passed_time":1.369447952,"remaining_time":6.880238508},
{"learn":[61.08747511],"iteration":166,"passed_time":1.375468995,"remaining_time":6.860872291},
{"learn":[61.06872032],"iteration":167,"passed_time":1.3810939,"remaining_time":6.839703123},
{"learn":[61.04267138],"iteration":168,"passed_time":1.386845537,"remaining_time":6.819341074},
{"learn":[61.01204541],"iteration":169,"passed_time":1.392803307,"remaining_time":6.800157322},
{"learn":[60.99332347],"iteration":170,"passed_time":1.398535858,"remaining_time":6.780036409},
{"learn":[60.96058078],"iteration":171,"passed_time":1.404440885,"remaining_time":6.760913096},
{"learn":[60.93019611],"iteration":172,"passed_time":1.409590288,"remaining_time":6.738330453},
{"learn":[60.91049943],"iteration":173,"passed_time":1.414774491,"remaining_time":6.716113386},
{"learn":[60.89575227],"iteration":174,"passed_time":1.420859273,"remaining_time":6.698336573},
{"learn":[60.87922869],"iteration":175,"passed_time":1.426504193,"remaining_time":6.678633266},
{"learn":[60.85865931],"iteration":176,"passed_time":1.432082488,"remaining_time":6.658779024},
{"learn":[60.84140977],"iteration":177,"passed_time":1.437831711,"remaining_time":6.639874531},
{"learn":[60.81932426],"iteration":178,"passed_time":1.442726662,"remaining_time":6.617198823},
{"learn":[60.80174107],"iteration":179,"passed_time":1.447904834,"remaining_time":6.596010911},
{"learn":[60.78822008],"iteration":180,"passed_time":1.453748472,"remaining_time":6.57801104},
{"learn":[60.76810744],"iteration":181,"passed_time":1.458973951,"remaining_time":6.55736644},
{"learn":[60.74183061],"iteration":182,"passed_time":1.464105177,"remaining_time":6.536469561},
{"learn":[60.72662665],"iteration":183,"passed_time":1.469910063,"remaining_time":6.518731585},
{"learn":[60.70473637],"iteration":184,"passed_time":1.475320625,"remaining_time":6.499385454},
{"learn":[60.68699577],"iteration":185,"passed_time":1.480955221,"remaining_time":6.481169624},
{"learn":[60.66775291],"iteration":186,"passed_time":1.486533228,"remaining_time":6.462842325},
{"learn":[60.65401356],"iteration":187,"passed_time":1.491826328,"remaining_time":6.443420099},
{"learn":[60.64061639],"iteration":188,"passed_time":1.496988635,"remaining_time":6.423586153},
{"learn":[60.62501885],"iteration":189,"passed_time":1.502803746,"remaining_time":6.406689653},
{"learn":[60.61097861],"iteration":190,"passed_time":1.508724559,"remaining_time":6.390356902},
{"learn":[60.58442866],"iteration":191,"passed_time":1.514371796,"remaining_time":6.372981309},
{"learn":[60.57000788],"iteration":192,"passed_time":1.519964985,"remaining_time":6.35550126},
{"learn":[60.54464871],"iteration":193,"passed_time":1.525626616,"remaining_time":6.338428106},
{"learn":[60.51893102],"iteration":194,"passed_time":1.53175015,"remaining_time":6.323378823},
{"learn":[60.50266701],"iteration":195,"passed_time":1.537598024,"remaining_time":6.307289854},
{"learn":[60.4879739],"iteration":196,"passed_time":1.543509592,"remaining_time":6.29156448},
{"learn":[60.46357124],"iteration":197,"passed_time":1.550879273,"remaining_time":6.281844328},
{"learn":[60.44602861],"iteration":198,"passed_time":1.557011801,"remaining_time":6.267168105},
{"learn":[60.42838215],"iteration":199,"passed_time":1.563284358,"remaining_time":6.253137433},
{"learn":[60.41637105],"iteration":200,"passed_time":1.569416616,"remaining_time":6.23862625},
{"learn":[60.40173465],"iteration":201,"passed_time":1.575382192,"remaining_time":6.223539552},
{"learn":[60.38634381],"iteration":202,"passed_time":1.581667043,"remaining_time":6.209796225},
{"learn":[60.36205283],"iteration":203,"passed_time":1.587956948,"remaining_time":6.19614574},
{"learn":[60.34303344],"iteration":204,"passed_time":1.594569956,"remaining_time":6.183820073},
{"learn":[60.3147415],"iteration":205,"passed_time":1.601174364,"remaining_time":6.171516722},
{"learn":[60.29484619],"iteration":206,"passed_time":1.606989214,"remaining_time":6.156243705},
{"learn":[60.28244591],"iteration":207,"passed_time":1.61407394,"remaining_time":6.145896925},
{"learn":[60.26718044],"iteration":208,"passed_time":1.620999261,"remaining_time":6.134978064},
{"learn":[60.25535518],"iteration":209,"passed_time":1.628452329,"remaining_time":6.126082573},
{"learn":[60.23705149],"iteration":210,"passed_time":1.636272239,"remaining_time":6.118572496},
{"learn":[60.22102366],"iteration":211,"passed_time":1.644236802,"remaining_time":6.111597171},
{"learn":[60.20836389],"iteration":212,"passed_time":1.652606693,"remaining_time":6.106110177},
{"learn":[60.18886537],"iteration":213,"passed_time":1.661937616,"remaining_time":6.10412601},
{"learn":[60.16526878],"iteration":214,"passed_time":1.674160173,"remaining_time":6.11263133},
{"learn":[60.15597531],"iteration":215,"passed_time":1.683113747,"remaining_time":6.109079527},
{"learn":[60.1430944],"iteration":216,"passed_time":1.690959383,"remaining_time":6.10148017},
{"learn":[60.12877657],"iteration":217,"passed_time":1.698690163,"remaining_time":6.093466547},
{"learn":[60.11641975],"iteration":218,"passed_time":1.706217395,"remaining_time":6.084729615},
{"learn":[60.09326979],"iteration":219,"passed_time":1.713651836,"remaining_time":6.075674692},
{"learn":[60.08216501],"iteration":220,"passed_time":1.72049816,"remaining_time":6.064561389},
{"learn":[60.06777584],"iteration":221,"passed_time":1.728244067,"remaining_time":6.056639119},
{"learn":[60.05601255],"iteration":222,"passed_time":1.737308781,"remaining_time":6.053313554},
{"learn":[60.04066782],"iteration":223,"passed_time":1.744689153,"remaining_time":6.044101709},
{"learn":[60.02892101],"iteration":224,"passed_time":1.752658056,"remaining_time":6.036933304},
{"learn":[60.01426067],"iteration":225,"passed_time":1.76049311,"remaining_time":6.029299411},
{"learn":[60.00168503],"iteration":226,"passed_time":1.767637163,"remaining_time":6.019310692},
{"learn":[59.98994383],"iteration":227,"passed_time":1.775214237,"remaining_time":6.010813117},
{"learn":[59.97298635],"iteration":228,"passed_time":1.782957792,"remaining_time":6.002884094},
{"learn":[59.95703474],"iteration":229,"passed_time":1.789939249,"remaining_time":5.99240531},
{"learn":[59.94612646],"iteration":230,"passed_time":1.797798622,"remaining_time":5.984879397},
{"learn":[59.93253309],"iteration":231,"passed_time":1.80436258,"remaining_time":5.973062335},
{"learn":[59.91516239],"iteration":232,"passed_time":1.811411527,"remaining_time":5.962886871},
{"learn":[59.90266473],"iteration":233,"passed_time":1.817109363,"remaining_time":5.948315264},
{"learn":[59.88682308],"iteration":234,"passed_time":1.822770615,"remaining_time":5.933700086},
{"learn":[59.87403952],"iteration":235,"passed_time":1.828579754,"remaining_time":5.919639542},
{"learn":[59.8598189],"iteration":236,"passed_time":1.834389776,"remaining_time":5.905651473},
{"learn":[59.85114752],"iteration":237,"passed_time":1.840176223,"remaining_time":5.891656646},
{"learn":[59.83947135],"iteration":238,"passed_time":1.846364091,"remaining_time":5.879008676},
{"learn":[59.82501144],"iteration":239,"passed_time":1.852435402,"remaining_time":5.866045439},
{"learn":[59.8163063],"iteration":240,"passed_time":1.859510427,"remaining_time":5.856300473},
{"learn":[59.80407437],"iteration":241,"passed_time":1.865428973,"remaining_time":5.842955212},
{"learn":[59.79420386],"iteration":242,"passed_time":1.87203698,"remaining_time":5.831818905},
{"learn":[59.77673547],"iteration":243,"passed_time":1.879044123,"remaining_time":5.82195638},
{"learn":[59.76077656],"iteration":244,"passed_time":1.885578526,"remaining_time":5.810660356},
{"learn":[59.74951754],"iteration":245,"passed_time":1.892485081,"remaining_time":5.800543705},
{"learn":[59.73986415],"iteration":246,"passed_time":1.898694292,"remaining_time":5.788327133},
{"learn":[59.7239846],"iteration":247,"passed_time":1.904381474,"remaining_time":5.774576084},
{"learn":[59.71480958],"iteration":248,"passed_time":1.910866636,"remaining_time":5.76329656},
{"learn":[59.70329432],"iteration":249,"passed_time":1.916266945,"remaining_time":5.748800836},
{"learn":[59.69275643],"iteration":250,"passed_time":1.922059665,"remaining_time":5.735548562},
{"learn":[59.67687931],"iteration":251,"passed_time":1.92796114,"remaining_time":5.722678306},
{"learn":[59.66338997],"iteration":252,"passed_time":1.934454573,"remaining_time":5.711610933},
{"learn":[59.65054622],"iteration":253,"passed_time":1.940949727,"remaining_time":5.700584632},
{"learn":[59.63882701],"iteration":254,"passed_time":1.947019338,"remaining_time":5.688350616},
{"learn":[59.62887336],"iteration":255,"passed_time":1.953736284,"remaining_time":5.678046077},
{"learn":[59.61340215],"iteration":256,"passed_time":1.959569703,"remaining_time":5.665215133},
{"learn":[59.60275821],"iteration":257,"passed_time":1.96564145,"remaining_time":5.65312386},
{"learn":[59.59305886],"iteration":258,"passed_time":1.971404524,"remaining_time":5.640195953},
{"learn":[59.57906841],"iteration":259,"passed_time":1.977142724,"remaining_time":5.627252368},
{"learn":[59.56377787],"iteration":260,"passed_time":1.98304715,"remaining_time":5.61483465},
{"learn":[59.5538839],"iteration":261,"passed_time":1.989091424,"remaining_time":5.602860577},
{"learn":[59.54256067],"iteration":262,"passed_time":1.995252089,"remaining_time":5.591257754},
{"learn":[59.53503627],"iteration":263,"passed_time":2.001505054,"remaining_time":5.579953484},
{"learn":[59.5196331],"iteration":264,"passed_time":2.007194856,"remaining_time":5.567125356},
{"learn":[59.50846551],"iteration":265,"passed_time":2.013403454,"remaining_time":5.555782462},
{"learn":[59.49801518],"iteration":266,"passed_time":2.019663442,"remaining_time":5.544619113},
{"learn":[59.47961331],"iteration":267,"passed_time":2.02567788,"remaining_time":5.532821673},
{"learn":[59.4687538],"iteration":268,"passed_time":2.031406576,"remaining_time":5.520290733},
{"learn":[59.45542115],"iteration":269,"passed_time":2.037351078,"remaining_time":5.508393655},
{"learn":[59.44191453],"iteration":270,"passed_time":2.043687339,"remaining_time":5.497594354},
{"learn":[59.43220066],"iteration":271,"passed_time":2.049569042,"remaining_time":5.485611261},
{"learn":[59.4235433],"iteration":272,"passed_time":2.055575836,"remaining_time":5.47400598},
{"learn":[59.40965861],"iteration":273,"passed_time":2.061402662,"remaining_time":5.461964716},
{"learn":[59.40285621],"iteration":274,"passed_time":2.067304326,"remaining_time":5.450165949},
{"learn":[59.3878024],"iteration":275,"passed_time":2.073811197,"remaining_time":5.439997487},
{"learn":[59.37730901],"iteration":276,"passed_time":2.079488878,"remaining_time":5.427691186},
{"learn":[59.36886408],"iteration":277,"passed_time":2.086024228,"remaining_time":5.417660046},
{"learn":[59.35725668],"iteration":278,"passed_time":2.091827765,"remaining_time":5.405762791},
{"learn":[59.34723554],"iteration":279,"passed_time":2.098029346,"remaining_time":5.394932604},
{"learn":[59.33640366],"iteration":280,"passed_time":2.103884132,"remaining_time":5.383248011},
{"learn":[59.3215307],"iteration":281,"passed_time":2.109617198,"remaining_time":5.371294853},
{"learn":[59.31121413],"iteration":282,"passed_time":2.115522506,"remaining_time":5.359822039},
{"learn":[59.30576972],"iteration":283,"passed_time":2.12151966,"remaining_time":5.348619987},
{"learn":[59.29372475],"iteration":284,"passed_time":2.127461752,"remaining_time":5.337316325},
{"learn":[59.27761148],"iteration":285,"passed_time":2.13459663,"remaining_time":5.329027951},
{"learn":[59.27052828],"iteration":286,"passed_time":2.14066553,"remaining_time":5.318099382},
{"learn":[59.25647339],"iteration":287,"passed_time":2.148269824,"remaining_time":5.311000397},
{"learn":[59.24588329],"iteration":288,"passed_time":2.154641927,"remaining_time":5.300866471},
{"learn":[59.23659474],"iteration":289,"passed_time":2.161452531,"remaining_time":5.291832059},
{"learn":[59.21558573],"iteration":290,"passed_time":2.168089036,"remaining_time":5.282388751},
{"learn":[59.2065689],"iteration":291,"passed_time":2.174107866,"remaining_time":5.271467018},
{"learn":[59.1973841],"iteration":292,"passed_time":2.181975043,"remaining_time":5.265038755},
{"learn":[59.18461999],"iteration":293,"passed_time":2.188870377,"remaining_time":5.256266961},
{"learn":[59.17202056],"iteration":294,"passed_time":2.196077858,"remaining_time":5.248253865},
{"learn":[59.15588905],"iteration":295,"passed_time":2.202469504,"remaining_time":5.238305846},
{"learn":[59.14818761],"iteration":296,"passed_time":2.208717992,"remaining_time":5.228042924},
{"learn":[59.13774218],"iteration":297,"passed_time":2.21435327,"remaining_time":5.216362401},
{"learn":[59.11852642],"iteration":298,"passed_time":2.219834681,"remaining_time":5.204361577},
{"learn":[59.1065455],"iteration":299,"passed_time":2.226349373,"remaining_time":5.194815203},
{"learn":[59.09708258],"iteration":300,"passed_time":2.232110215,"remaining_time":5.183538341},
{"learn":[59.09080323],"iteration":301,"passed_time":2.2379137,"remaining_time":5.172396564},
{"learn":[59.08071502],"iteration":302,"passed_time":2.243919319,"remaining_time":5.161755002},
{"learn":[59.07279605],"iteration":303,"passed_time":2.249943022,"remaining_time":5.15118534},
{"learn":[59.06134036],"iteration":304,"passed_time":2.255753447,"remaining_time":5.140159495},
{"learn":[59.05060545],"iteration":305,"passed_time":2.261698608,"remaining_time":5.129473315},
{"learn":[59.04420103],"iteration":306,"passed_time":2.267291197,"remaining_time":5.118022147},
{"learn":[59.03116934],"iteration":307,"passed_time":2.273177541,"remaining_time":5.107269021},
{"learn":[59.01591557],"iteration":308,"passed_time":2.27922122,"remaining_time":5.096899233},
{"learn":[59.00396723],"iteration":309,"passed_time":2.285078039,"remaining_time":5.086141441},
{"learn":[58.99469177],"iteration":310,"passed_time":2.290839272,"remaining_time":5.075203403},
{"learn":[58.98859489],"iteration":311,"passed_time":2.29675987,"remaining_time":5.06464997},
{"learn":[58.98193765],"iteration":312,"passed_time":2.30244552,"remaining_time":5.053610455},
{"learn":[58.97397345],"iteration":313,"passed_time":2.307674836,"remaining_time":5.041608081},
{"learn":[58.96278199],"iteration":314,"passed_time":2.313011747,"remaining_time":5.029882688},
{"learn":[58.95365081],"iteration":315,"passed_time":2.319009831,"remaining_time":5.019628875},
{"learn":[58.94365185],"iteration":316,"passed_time":2.32463019,"remaining_time":5.008588074},
{"learn":[58.93108686],"iteration":317,"passed_time":2.331626456,"remaining_time":5.000532212},
{"learn":[58.91637905],"iteration":318,"passed_time":2.337322458,"remaining_time":4.989707191},
{"learn":[58.90274704],"iteration":319,"passed_time":2.343164412,"remaining_time":4.979224376},
{"learn":[58.89717401],"iteration":320,"passed_time":2.348341182,"remaining_time":4.967363435},
{"learn":[58.88706475],"iteration":321,"passed_time":2.35388448,"remaining_time":4.956315769},
{"learn":[58.87111773],"iteration":322,"passed_time":2.359350918,"remaining_time":4.945141089},
{"learn":[58.86518297],"iteration":323,"passed_time":2.364392408,"remaining_time":4.933115024},
{"learn":[58.85129303],"iteration":324,"passed_time":2.369865651,"remaining_time":4.922028661},
{"learn":[58.84331386],"iteration":325,"passed_time":2.375791062,"remaining_time":4.911911582},
{"learn":[58.82835018],"iteration":326,"passed_time":2.381973746,"remaining_time":4.902349637},
{"learn":[58.82026556],"iteration":327,"passed_time":2.388084547,"remaining_time":4.892661024},
{"learn":[58.80692728],"iteration":328,"passed_time":2.393323088,"remaining_time":4.881215174},
{"learn":[58.79833429],"iteration":329,"passed_time":2.39872781,"remaining_time":4.870144341},
{"learn":[58.78553923],"iteration":330,"passed_time":2.403963199,"remaining_time":4.858765498},
{"learn":[58.7726782],"iteration":331,"passed_time":2.40924522,"remaining_time":4.847517491},
{"learn":[58.76256641],"iteration":332,"passed_time":2.414087385,"remaining_time":4.835424282},
{"learn":[58.75079513],"iteration":333,"passed_time":2.419468158,"remaining_time":4.824448482},
{"learn":[58.73985735],"iteration":334,"passed_time":2.424681384,"remaining_time":4.813173495},
{"learn":[58.72704773],"iteration":335,"passed_time":2.430454687,"remaining_time":4.803041406},
{"learn":[58.71598205],"iteration":336,"passed_time":2.436286478,"remaining_time":4.793050252},
{"learn":[58.70419649],"iteration":337,"passed_time":2.44214787,"remaining_time":4.783141686},
{"learn":[58.68954966],"iteration":338,"passed_time":2.447877952,"remaining_time":4.773000963},
{"learn":[58.68044882],"iteration":339,"passed_time":2.45378349,"remaining_time":4.763226776},
{"learn":[58.67134114],"iteration":340,"passed_time":2.459785556,"remaining_time":4.753661823},
{"learn":[58.66632546],"iteration":341,"passed_time":2.466070137,"remaining_time":4.744661258},
{"learn":[58.65760799],"iteration":342,"passed_time":2.472547996,"remaining_time":4.736046744},
{"learn":[58.6497629],"iteration":343,"passed_time":2.478672092,"remaining_time":4.726770037},
{"learn":[58.63844734],"iteration":344,"passed_time":2.485434839,"remaining_time":4.718724115},
{"learn":[58.62612685],"iteration":345,"passed_time":2.49159339,"remaining_time":4.709543576},
{"learn":[58.61431785],"iteration":346,"passed_time":2.497593923,"remaining_time":4.700083089},
{"learn":[58.6061896],"iteration":347,"passed_time":2.503448409,"remaining_time":4.690368857},
{"learn":[58.59378387],"iteration":348,"passed_time":2.509581778,"remaining_time":4.681196956},
{"learn":[58.56808948],"iteration":349,"passed_time":2.5167342,"remaining_time":4.673934942},
{"learn":[58.56344428],"iteration":350,"passed_time":2.523150826,"remaining_time":4.665313067},
{"learn":[58.55300177],"iteration":351,"passed_time":2.52989371,"remaining_time":4.657304329},
{"learn":[58.54467204],"iteration":352,"passed_time":2.536959184,"remaining_time":4.649894028},
{"learn":[58.53470718],"iteration":353,"passed_time":2.543943962,"remaining_time":4.642338416},
{"learn":[58.52710071],"iteration":354,"passed_time":2.55076279,"remaining_time":4.634484505},
{"learn":[58.51631022],"iteration":355,"passed_time":2.557713822,"remaining_time":4.626875567},
{"learn":[58.50540127],"iteration":356,"passed_time":2.564458539,"remaining_time":4.618898713},
{"learn":[58.48952335],"iteration":357,"passed_time":2.571126981,"remaining_time":4.610791961},
{"learn":[58.47767666],"iteration":358,"passed_time":2.578954463,"remaining_time":4.604762704},
{"learn":[58.46400452],"iteration":359,"passed_time":2.586982088,"remaining_time":4.599079268},
{"learn":[58.45503382],"iteration":360,"passed_time":2.595436573,"remaining_time":4.594138421},
{"learn":[58.44676271],"iteration":361,"passed_time":2.604130044,"remaining_time":4.589599359},
{"learn":[58.43448651],"iteration":362,"passed_time":2.613962118,"remaining_time":4.587035453},
{"learn":[58.42210164],"iteration":363,"passed_time":2.624255787,"remaining_time":4.585238133},
{"learn":[58.41343748],"iteration":364,"passed_time":2.633675124,"remaining_time":4.581873161},
{"learn":[58.40188482],"iteration":365,"passed_time":2.644176155,"remaining_time":4.580348859},
{"learn":[58.38920031],"iteration":366,"passed_time":2.654112369,"remaining_time":4.577801443},
{"learn":[58.37482116],"iteration":367,"passed_time":2.663212376,"remaining_time":4.573777776},
{"learn":[58.36230946],"iteration":368,"passed_time":2.674631583,"remaining_time":4.573692491},
{"learn":[58.3574202],"iteration":369,"passed_time":2.68649392,"remaining_time":4.574300458},
{"learn":[58.35232172],"iteration":370,"passed_time":2.697370042,"remaining_time":4.573169155},
{"learn":[58.3288535],"iteration":371,"passed_time":2.708892058,"remaining_time":4.573075839},
{"learn":[58.32062856],"iteration":372,"passed_time":2.721101093,"remaining_time":4.5740761},
{"learn":[58.31053419],"iteration":373,"passed_time":2.732162818,"remaining_time":4.573085359},
{"learn":[58.30159618],"iteration":374,"passed_time":2.741812551,"remaining_time":4.569687585},
{"learn":[58.2919391],"iteration":375,"passed_time":2.753790509,"remaining_time":4.57012042},
{"learn":[58.28413979],"iteration":376,"passed_time":2.764932007,"remaining_time":4.569105146},
{"learn":[58.27646838],"iteration":377,"passed_time":2.776556182,"remaining_time":4.568830542},
{"learn":[58.26888664],"iteration":378,"passed_time":2.787479761,"remaining_time":4.567348105},
{"learn":[58.25841869],"iteration":379,"passed_time":2.799860066,"remaining_time":4.568192739},
{"learn":[58.24778729],"iteration":380,"passed_time":2.812017855,"remaining_time":4.568606437},
{"learn":[58.23834212],"iteration":381,"passed_time":2.824880765,"remaining_time":4.570095059},
{"learn":[58.23453446],"iteration":382,"passed_time":2.834739857,"remaining_time":4.566669692},
{"learn":[58.22453708],"iteration":383,"passed_time":2.843833045,"remaining_time":4.561982176},
{"learn":[58.21053968],"iteration":384,"passed_time":2.853811586,"remaining_time":4.55868604},
{"learn":[58.20539987],"iteration":385,"passed_time":2.862918705,"remaining_time":4.553969131},
{"learn":[58.1948575],"iteration":386,"passed_time":2.871393196,"remaining_time":4.548227466},
{"learn":[58.18346982],"iteration":387,"passed_time":2.880267179,"remaining_time":4.543101839},
{"learn":[58.17465512],"iteration":388,"passed_time":2.88856816,"remaining_time":4.537056931},
{"learn":[58.16082246],"iteration":389,"passed_time":2.896430637,"remaining_time":4.530314587},
{"learn":[58.15017554],"iteration":390,"passed_time":2.90371249,"remaining_time":4.522662164},
{"learn":[58.13618072],"iteration":391,"passed_time":2.911478791,"remaining_time":4.515763023},
{"learn":[58.12841011],"iteration":392,"passed_time":2.918542814,"remaining_time":4.507774778},
{"learn":[58.1160953],"iteration":393,"passed_time":2.926066736,"remaining_time":4.500498584},
{"learn":[58.10319612],"iteration":394,"passed_time":2.933397047,"remaining_time":4.492924591},
{"learn":[58.09028914],"iteration":395,"passed_time":2.940780265,"remaining_time":4.485432525},
{"learn":[58.08414132],"iteration":396,"passed_time":2.947310924,"remaining_time":4.476646064},
{"learn":[58.07015572],"iteration":397,"passed_time":2.953714342,"remaining_time":4.467678478},
{"learn":[58.05405349],"iteration":398,"passed_time":2.959905741,"remaining_time":4.458404387},
{"learn":[58.04272031],"iteration":399,"passed_time":2.965110747,"remaining_time":4.447666121},
{"learn":[58.03665446],"iteration":400,"passed_time":2.970698238,"remaining_time":4.437526794},
{"learn":[58.02582933],"iteration":401,"passed_time":2.976010005,"remaining_time":4.426999958},
{"learn":[58.01661978],"iteration":402,"passed_time":2.98146591,"remaining_time":4.416712527},
{"learn":[58.00824332],"iteration":403,"passed_time":2.987329868,"remaining_time":4.407050994},
{"learn":[57.9975921],"iteration":404,"passed_time":2.992732226,"remaining_time":4.396730061},
{"learn":[57.98052963],"iteration":405,"passed_time":2.997931814,"remaining_time":4.386136693},
{"learn":[57.96935274],"iteration":406,"passed_time":3.003514869,"remaining_time":4.376128543},
{"learn":[57.96207534],"iteration":407,"passed_time":3.009158049,"remaining_time":4.366229326},
{"learn":[57.95446029],"iteration":408,"passed_time":3.0148444,"remaining_time":4.356413302},
{"learn":[57.94720622],"iteration":409,"passed_time":3.020734131,"remaining_time":4.346910091},
{"learn":[57.93498199],"iteration":410,"passed_time":3.026691975,"remaining_time":4.337522076},
{"learn":[57.93030311],"iteration":411,"passed_time":3.032609993,"remaining_time":4.328093873},
{"learn":[57.91927317],"iteration":412,"passed_time":3.038676308,"remaining_time":4.318893444},
{"learn":[57.91151986],"iteration":413,"passed_time":3.044165517,"remaining_time":4.308891288},
{"learn":[57.90284263],"iteration":414,"passed_time":3.050121478,"remaining_time":4.299568831},
{"learn":[57.89103816],"iteration":415,"passed_time":3.056289535,"remaining_time":4.290560308},
{"learn":[57.88367139],"iteration":416,"passed_time":3.062559422,"remaining_time":4.281707777},
{"learn":[57.87464047],"iteration":417,"passed_time":3.068761578,"remaining_time":4.272773298},
{"learn":[57.86059087],"iteration":418,"passed_time":3.074789066,"remaining_time":4.263609659},
{"learn":[57.85134011],"iteration":419,"passed_time":3.080783549,"remaining_time":4.254415377},
{"learn":[57.84306643],"iteration":420,"passed_time":3.087050435,"remaining_time":4.24561093},
{"learn":[57.83183107],"iteration":421,"passed_time":3.093107327,"remaining_time":4.236530889},
{"learn":[57.82355239],"iteration":422,"passed_time":3.099550176,"remaining_time":4.227991611},
{"learn":[57.81602036],"iteration":423,"passed_time":3.105651744,"remaining_time":4.218998595},
{"learn":[57.8083274],"iteration":424,"passed_time":3.112369194,"remaining_time":4.210852439},
{"learn":[57.79912801],"iteration":425,"passed_time":3.11829515,"remaining_time":4.201646517},
{"learn":[57.79614245],"iteration":426,"passed_time":3.124691955,"remaining_time":4.193087799},
{"learn":[57.7822724],"iteration":427,"passed_time":3.131268756,"remaining_time":4.184779739},
{"learn":[57.77094173],"iteration":428,"passed_time":3.137106153,"remaining_time":4.175495602},
{"learn":[57.76713139],"iteration":429,"passed_time":3.143216445,"remaining_time":4.166589241},
{"learn":[57.75633132],"iteration":430,"passed_time":3.149308231,"remaining_time":4.157671423},
{"learn":[57.74755516],"iteration":431,"passed_time":3.156256808,"remaining_time":4.149893211},
{"learn":[57.73030637],"iteration":432,"passed_time":3.162783247,"remaining_time":4.141566053},
{"learn":[57.72064703],"iteration":433,"passed_time":3.169101756,"remaining_time":4.132976023},
{"learn":[57.71321285],"iteration":434,"passed_time":3.176423574,"remaining_time":4.125699585},
{"learn":[57.70331515],"iteration":435,"passed_time":3.183727953,"remaining_time":4.11840038},
{"learn":[57.6952601],"iteration":436,"passed_time":3.190484178,"remaining_time":4.110394948},
{"learn":[57.68581383],"iteration":437,"passed_time":3.198316139,"remaining_time":4.103775503},
{"learn":[57.67704124],"iteration":438,"passed_time":3.206903931,"remaining_time":4.098116413},
{"learn":[57.67203006],"iteration":439,"passed_time":3.216769328,"remaining_time":4.094070054},
{"learn":[57.66380255],"iteration":440,"passed_time":3.226630042,"remaining_time":4.089991369},
{"learn":[57.65858157],"iteration":441,"passed_time":3.237311961,"remaining_time":4.086923245},
{"learn":[57.65143721],"iteration":442,"passed_time":3.247353047,"remaining_time":4.083015004},
{"learn":[57.6379548],"iteration":443,"passed_time":3.256871515,"remaining_time":4.07842469},
{"learn":[57.62725846],"iteration":444,"passed_time":3.266300293,"remaining_time":4.073700366},
{"learn":[57.61896473],"iteration":445,"passed_time":3.274355677,"remaining_time":4.06724898},
{"learn":[57.60985872],"iteration":446,"passed_time":3.282883726,"remaining_time":4.061375169},
{"learn":[57.60435235],"iteration":447,"passed_time":3.291078597,"remaining_time":4.055078985},
{"learn":[57.59577582],"iteration":448,"passed_time":3.299896839,"remaining_time":4.049539328},
{"learn":[57.58739561],"iteration":449,"passed_time":3.309551717,"remaining_time":4.045007654},
{"learn":[57.57371725],"iteration":450,"passed_time":3.318903775,"remaining_time":4.040084639},
{"learn":[57.56722881],"iteration":451,"passed_time":3.329708653,"remaining_time":4.036903411},
{"learn":[57.55775849],"iteration":452,"passed_time":3.340638423,"remaining_time":4.033839332},
{"learn":[57.55123546],"iteration":453,"passed_time":3.351883727,"remaining_time":4.031120077},
{"learn":[57.54251954],"iteration":454,"passed_time":3.363359853,"remaining_time":4.028639824},
{"learn":[57.52997305],"iteration":455,"passed_time":3.375135525,"remaining_time":4.026477468},
{"learn":[57.51827289],"iteration":456,"passed_time":3.38705651,"remaining_time":4.024445701},
{"learn":[57.51042735],"iteration":457,"passed_time":3.398286718,"remaining_time":4.021553278},
{"learn":[57.50054211],"iteration":458,"passed_time":3.409991046,"remaining_time":4.019183346},
{"learn":[57.49436608],"iteration":459,"passed_time":3.422291626,"remaining_time":4.017472778},
{"learn":[57.48391725],"iteration":460,"passed_time":3.433641085,"remaining_time":4.014604218},
{"learn":[57.47282638],"iteration":461,"passed_time":3.444791549,"remaining_time":4.011467216},
{"learn":[57.46317657],"iteration":462,"passed_time":3.459864186,"remaining_time":4.012844639},
{"learn":[57.45397599],"iteration":463,"passed_time":3.471051544,"remaining_time":4.00966299},
{"learn":[57.44850073],"iteration":464,"passed_time":3.481447838,"remaining_time":4.00553676},
{"learn":[57.43785322],"iteration":465,"passed_time":3.491949539,"remaining_time":4.001504408},
{"learn":[57.43224233],"iteration":466,"passed_time":3.501438909,"remaining_time":3.996288947},
{"learn":[57.42445073],"iteration":467,"passed_time":3.51056773,"remaining_time":3.990645368},
{"learn":[57.41369455],"iteration":468,"passed_time":3.519062444,"remaining_time":3.984268994},
{"learn":[57.40607998],"iteration":469,"passed_time":3.527686837,"remaining_time":3.978029837},
{"learn":[57.39414034],"iteration":470,"passed_time":3.536176547,"remaining_time":3.971629285},
{"learn":[57.38632286],"iteration":471,"passed_time":3.543217878,"remaining_time":3.96359966},
{"learn":[57.37933817],"iteration":472,"passed_time":3.550946067,"remaining_time":3.956339487},
{"learn":[57.36910538],"iteration":473,"passed_time":3.558412248,"remaining_time":3.948786588},
{"learn":[57.3632701],"iteration":474,"passed_time":3.565186515,"remaining_time":3.940469306},
{"learn":[57.35836617],"iteration":475,"passed_time":3.572360707,"remaining_time":3.932598762},
{"learn":[57.35293954],"iteration":476,"passed_time":3.579295754,"remaining_time":3.92446893},
{"learn":[57.3427306],"iteration":477,"passed_time":3.585962245,"remaining_time":3.91605082},
{"learn":[57.32906923],"iteration":478,"passed_time":3.593091368,"remaining_time":3.908143221},
{"learn":[57.3188375],"iteration":479,"passed_time":3.600044821,"remaining_time":3.900048556},
{"learn":[57.30984133],"iteration":480,"passed_time":3.607545402,"remaining_time":3.892548989},
{"learn":[57.29897383],"iteration":481,"passed_time":3.614370027,"remaining_time":3.884322975},
{"learn":[57.28923147],"iteration":482,"passed_time":3.620390788,"remaining_time":3.875242313},
{"learn":[57.28061345],"iteration":483,"passed_time":3.626695432,"remaining_time":3.866476949},
{"learn":[57.277225],"iteration":484,"passed_time":3.633163438,"remaining_time":3.857895197},
{"learn":[57.2674479],"iteration":485,"passed_time":3.638798535,"remaining_time":3.848441249},
{"learn":[57.26106836],"iteration":486,"passed_time":3.64440111,"remaining_time":3.838968725},
{"learn":[57.24861869],"iteration":487,"passed_time":3.650108737,"remaining_time":3.829622282},
{"learn":[57.23723321],"iteration":488,"passed_time":3.655606741,"remaining_time":3.820071666},
{"learn":[57.22681122],"iteration":489,"passed_time":3.66118142,"remaining_time":3.810617396},
{"learn":[57.21785566],"iteration":490,"passed_time":3.667620436,"remaining_time":3.802074953},
{"learn":[57.2118013],"iteration":491,"passed_time":3.674053819,"remaining_time":3.793535244},
{"learn":[57.20321657],"iteration":492,"passed_time":3.679682707,"remaining_time":3.784176739},
{"learn":[57.19733662],"iteration":493,"passed_time":3.685585198,"remaining_time":3.775113583},
{"learn":[57.19093032],"iteration":494,"passed_time":3.691697802,"remaining_time":3.766277555},
{"learn":[57.18066201],"iteration":495,"passed_time":3.698511575,"remaining_time":3.758164987},
{"learn":[57.17356288],"iteration":496,"passed_time":3.705162198,"remaining_time":3.749892526},
{"learn":[57.16727131],"iteration":497,"passed_time":3.711450911,"remaining_time":3.741261762},
{"learn":[57.16158159],"iteration":498,"passed_time":3.717759845,"remaining_time":3.732660686},
{"learn":[57.15540103],"iteration":499,"passed_time":3.723413112,"remaining_time":3.723413112},
{"learn":[57.14799082],"iteration":500,"passed_time":3.730029062,"remaining_time":3.715138726},
{"learn":[57.14195524],"iteration":501,"passed_time":3.736041279,"remaining_time":3.706272026},
{"learn":[57.12620704],"iteration":502,"passed_time":3.743028911,"remaining_time":3.698380455},
{"learn":[57.12242604],"iteration":503,"passed_time":3.750148864,"remaining_time":3.690622691},
{"learn":[57.10728722],"iteration":504,"passed_time":3.756446026,"remaining_time":3.682060957},
{"learn":[57.09619523],"iteration":505,"passed_time":3.762534964,"remaining_time":3.673304886},
{"learn":[57.08758196],"iteration":506,"passed_time":3.768409863,"remaining_time":3.664351208},
{"learn":[57.07913158],"iteration":507,"passed_time":3.773941972,"remaining_time":3.655077658},
{"learn":[57.07369832],"iteration":508,"passed_time":3.779552164,"remaining_time":3.64589413},
{"learn":[57.06515032],"iteration":509,"passed_time":3.785751007,"remaining_time":3.637290184},
{"learn":[57.05876823],"iteration":510,"passed_time":3.791515277,"remaining_time":3.628279786},
{"learn":[57.04683355],"iteration":511,"passed_time":3.797303886,"remaining_time":3.619305266},
{"learn":[57.03915963],"iteration":512,"passed_time":3.803396034,"remaining_time":3.610631323},
{"learn":[57.03187924],"iteration":513,"passed_time":3.80911507,"remaining_time":3.601614638},
{"learn":[57.02446828],"iteration":514,"passed_time":3.815190517,"remaining_time":3.592946409},
{"learn":[57.01140022],"iteration":515,"passed_time":3.820930313,"remaining_time":3.583973395},
{"learn":[57.00595174],"iteration":516,"passed_time":3.827097909,"remaining_time":3.575412553},
{"learn":[56.99712831],"iteration":517,"passed_time":3.832721125,"remaining_time":3.566354406},
{"learn":[56.99258088],"iteration":518,"passed_time":3.838227142,"remaining_time":3.557200877},
{"learn":[56.98502526],"iteration":519,"passed_time":3.844046053,"remaining_time":3.548350203},
{"learn":[56.97713976],"iteration":520,"passed_time":3.849380156,"remaining_time":3.539065441},
{"learn":[56.97198588],"iteration":521,"passed_time":3.855207869,"remaining_time":3.530247819},
{"learn":[56.96851193],"iteration":522,"passed_time":3.860820622,"remaining_time":3.521245577},
{"learn":[56.96336239],"iteration":523,"passed_time":3.86618603,"remaining_time":3.512031584},
{"learn":[56.95843712],"iteration":524,"passed_time":3.872058855,"remaining_time":3.503291345},
{"learn":[56.95082728],"iteration":525,"passed_time":3.877601602,"remaining_time":3.494264561},
{"learn":[56.9428132],"iteration":526,"passed_time":3.882977447,"remaining_time":3.4851012},
{"learn":[56.93621134],"iteration":527,"passed_time":3.888787174,"remaining_time":3.47634005},
{"learn":[56.93179667],"iteration":528,"passed_time":3.89466361,"remaining_time":3.467649452},
{"learn":[56.92559287],"iteration":529,"passed_time":3.900225267,"remaining_time":3.458690331},
{"learn":[56.92039701],"iteration":530,"passed_time":3.90617885,"remaining_time":3.450090171},
{"learn":[56.9117887],"iteration":531,"passed_time":3.912353887,"remaining_time":3.441694773},
{"learn":[56.90111657],"iteration":532,"passed_time":3.918313258,"remaining_time":3.433118746},
{"learn":[56.89239532],"iteration":533,"passed_time":3.924707138,"remaining_time":3.424931697},
{"learn":[56.88644858],"iteration":534,"passed_time":3.930999333,"remaining_time":3.416662971},
{"learn":[56.87741607],"iteration":535,"passed_time":3.937390142,"remaining_time":3.408486989},
{"learn":[56.8703218],"iteration":536,"passed_time":3.943745486,"remaining_time":3.400287077},
{"learn":[56.86002903],"iteration":537,"passed_time":3.950769065,"remaining_time":3.392667859},
{"learn":[56.85255373],"iteration":538,"passed_time":3.962460339,"remaining_time":3.389043073},
{"learn":[56.8447946],"iteration":539,"passed_time":3.971855259,"remaining_time":3.383432258},
{"learn":[56.84136122],"iteration":540,"passed_time":3.980425597,"remaining_time":3.377107854},
{"learn":[56.83544884],"iteration":541,"passed_time":3.9869582,"remaining_time":3.369053239},
{"learn":[56.830446],"iteration":542,"passed_time":3.992887435,"remaining_time":3.360496423},
{"learn":[56.8247438],"iteration":543,"passed_time":3.998566994,"remaining_time":3.351739981},
{"learn":[56.81653791],"iteration":544,"passed_time":4.00430541,"remaining_time":3.343043966},
{"learn":[56.80598846],"iteration":545,"passed_time":4.011098789,"remaining_time":3.335235989},
{"learn":[56.79968245],"iteration":546,"passed_time":4.016341857,"remaining_time":3.326147827},
{"learn":[56.79269148],"iteration":547,"passed_time":4.023070004,"remaining_time":3.318298616},
{"learn":[56.78255087],"iteration":548,"passed_time":4.029406174,"remaining_time":3.310131484},
{"learn":[56.77387168],"iteration":549,"passed_time":4.035760836,"remaining_time":3.301986138},
{"learn":[56.75948626],"iteration":550,"passed_time":4.041615781,"remaining_time":3.293440083},
{"learn":[56.75055685],"iteration":551,"passed_time":4.047095055,"remaining_time":3.284598885},
{"learn":[56.74472799],"iteration":552,"passed_time":4.053140936,"remaining_time":3.276227845},
{"learn":[56.73752298],"iteration":553,"passed_time":4.058911374,"remaining_time":3.267643453},
{"learn":[56.73040139],"iteration":554,"passed_time":4.065244816,"remaining_time":3.259520618},
{"learn":[56.7242897],"iteration":555,"passed_time":4.07161739,"remaining_time":3.251435469},
{"learn":[56.71683705],"iteration":556,"passed_time":4.077736045,"remaining_time":3.243154521},
{"learn":[56.70926931],"iteration":557,"passed_time":4.083922402,"remaining_time":3.234934949},
{"learn":[56.69887107],"iteration":558,"passed_time":4.090202397,"remaining_time":3.226796524},
{"learn":[56.69223847],"iteration":559,"passed_time":4.096257132,"remaining_time":3.218487747},
{"learn":[56.68630369],"iteration":560,"passed_time":4.102839174,"remaining_time":3.210599639},
{"learn":[56.67578147],"iteration":561,"passed_time":4.108261956,"remaining_time":3.201812698},
{"learn":[56.67063739],"iteration":562,"passed_time":4.114814899,"remaining_time":3.193914939},
{"learn":[56.66486962],"iteration":563,"passed_time":4.12143365,"remaining_time":3.186072821},
{"learn":[56.65665632],"iteration":564,"passed_time":4.128201722,"remaining_time":3.178349999},
{"learn":[56.64638934],"iteration":565,"passed_time":4.134910139,"remaining_time":3.170584806},
{"learn":[56.63706129],"iteration":566,"passed_time":4.142557062,"remaining_time":3.163540049},
{"learn":[56.6312934],"iteration":567,"passed_time":4.151506178,"remaining_time":3.157483572},
{"learn":[56.61959493],"iteration":568,"passed_time":4.158695357,"remaining_time":3.150083829},
{"learn":[56.61610817],"iteration":569,"passed_time":4.165613135,"remaining_time":3.142480085},
{"learn":[56.60804582],"iteration":570,"passed_time":4.172379595,"remaining_time":3.134765055},
{"learn":[56.60167002],"iteration":571,"passed_time":4.179168138,"remaining_time":3.127069865},
{"learn":[56.59889519],"iteration":572,"passed_time":4.186330773,"remaining_time":3.119656615},
{"learn":[56.59139194],"iteration":573,"passed_time":4.192479757,"remaining_time":3.111491945},
{"learn":[56.58231311],"iteration":574,"passed_time":4.199351452,"remaining_time":3.103868465},
{"learn":[56.57476851],"iteration":575,"passed_time":4.206586135,"remaining_time":3.096514794},
{"learn":[56.56820097],"iteration":576,"passed_time":4.214261694,"remaining_time":3.089484743},
{"learn":[56.55258883],"iteration":577,"passed_time":4.220172365,"remaining_time":3.081163907},
{"learn":[56.54902556],"iteration":578,"passed_time":4.226536091,"remaining_time":3.073180819},
{"learn":[56.54134945],"iteration":579,"passed_time":4.233466831,"remaining_time":3.065613912},
{"learn":[56.53281286],"iteration":580,"passed_time":4.241075476,"remaining_time":3.05853808},
{"learn":[56.52551129],"iteration":581,"passed_time":4.24853512,"remaining_time":3.051353403},
{"learn":[56.51872652],"iteration":582,"passed_time":4.255813865,"remaining_time":3.044038391},
{"learn":[56.50594892],"iteration":583,"passed_time":4.264084029,"remaining_time":3.037429719},
{"learn":[56.49187178],"iteration":584,"passed_time":4.270043205,"remaining_time":3.029175949},
{"learn":[56.47974656],"iteration":585,"passed_time":4.276775205,"remaining_time":3.021475998},
{"learn":[56.46658073],"iteration":586,"passed_time":4.285224206,"remaining_time":3.014987389},
{"learn":[56.46017646],"iteration":587,"passed_time":4.291677351,"remaining_time":3.007093654},
{"learn":[56.45258103],"iteration":588,"passed_time":4.299807196,"remaining_time":3.000374801},
{"learn":[56.44582882],"iteration":589,"passed_time":4.306410822,"remaining_time":2.992590571},
{"learn":[56.43793777],"iteration":590,"passed_time":4.314085621,"remaining_time":2.98555164},
{"learn":[56.43268761],"iteration":591,"passed_time":4.320268131,"remaining_time":2.977482091},
{"learn":[56.41938446],"iteration":592,"passed_time":4.326788737,"remaining_time":2.969650954},
{"learn":[56.41221152],"iteration":593,"passed_time":4.334285405,"remaining_time":2.962491371},
{"learn":[56.40402772],"iteration":594,"passed_time":4.34066423,"remaining_time":2.95456977},
{"learn":[56.39711],"iteration":595,"passed_time":4.347602081,"remaining_time":2.947032283},
{"learn":[56.38980347],"iteration":596,"passed_time":4.353942579,"remaining_time":2.939093567},
{"learn":[56.38327752],"iteration":597,"passed_time":4.360287571,"remaining_time":2.931163216},
{"learn":[56.37453445],"iteration":598,"passed_time":4.367362348,"remaining_time":2.923726714},
{"learn":[56.36338926],"iteration":599,"passed_time":4.373998698,"remaining_time":2.915999132},
{"learn":[56.35604344],"iteration":600,"passed_time":4.381790468,"remaining_time":2.909042258},
{"learn":[56.35131612],"iteration":601,"passed_time":4.388823834,"remaining_time":2.901581206},
{"learn":[56.34511376],"iteration":602,"passed_time":4.396092454,"remaining_time":2.894276458},
{"learn":[56.34137961],"iteration":603,"passed_time":4.403355676,"remaining_time":2.886968291},
{"learn":[56.32955563],"iteration":604,"passed_time":4.410917094,"remaining_time":2.879854962},
{"learn":[56.31738242],"iteration":605,"passed_time":4.418711652,"remaining_time":2.872891734},
{"learn":[56.30843067],"iteration":606,"passed_time":4.427513603,"remaining_time":2.866578},
{"learn":[56.30260555],"iteration":607,"passed_time":4.434278386,"remaining_time":2.858942644},
{"learn":[56.29572569],"iteration":608,"passed_time":4.441120031,"remaining_time":2.851359494},
{"learn":[56.28888116],"iteration":609,"passed_time":4.447929699,"remaining_time":2.843758332},
{"learn":[56.28126777],"iteration":610,"passed_time":4.456547455,"remaining_time":2.8373109},
{"learn":[56.27594505],"iteration":611,"passed_time":4.463428468,"remaining_time":2.829755303},
{"learn":[56.26960682],"iteration":612,"passed_time":4.469133269,"remaining_time":2.82145934},
{"learn":[56.26501366],"iteration":613,"passed_time":4.475120215,"remaining_time":2.81334919},
{"learn":[56.25680651],"iteration":614,"passed_time":4.480994842,"remaining_time":2.805175633},
{"learn":[56.24926946],"iteration":615,"passed_time":4.486911749,"remaining_time":2.797035896},
{"learn":[56.24390392],"iteration":616,"passed_time":4.49339169,"remaining_time":2.789252864},
{"learn":[56.23760128],"iteration":617,"passed_time":4.500231581,"remaining_time":2.781696544},
{"learn":[56.23348478],"iteration":618,"passed_time":4.506781667,"remaining_time":2.77396416},
{"learn":[56.22631059],"iteration":619,"passed_time":4.513258065,"remaining_time":2.766190427},
{"learn":[56.21866421],"iteration":620,"passed_time":4.519506157,"remaining_time":2.758281535},
{"learn":[56.21526983],"iteration":621,"passed_time":4.526294073,"remaining_time":2.750706045},
{"learn":[56.20850431],"iteration":622,"passed_time":4.531978036,"remaining_time":2.742465039},
{"learn":[56.20439661],"iteration":623,"passed_time":4.538116294,"remaining_time":2.734505972},
{"learn":[56.20184056],"iteration":624,"passed_time":4.544163148,"remaining_time":2.726497889},
{"learn":[56.2017903],"iteration":625,"passed_time":4.547637768,"remaining_time":2.716959306},
{"learn":[56.19708999],"iteration":626,"passed_time":4.553164563,"remaining_time":2.708660896},
{"learn":[56.19216262],"iteration":627,"passed_time":4.559998441,"remaining_time":2.701145573},
{"learn":[56.18216804],"iteration":628,"passed_time":4.566883037,"remaining_time":2.693662332},
{"learn":[56.17454594],"iteration":629,"passed_time":4.574027574,"remaining_time":2.686333654},
{"learn":[56.16403944],"iteration":630,"passed_time":4.58032114,"remaining_time":2.678507925},
{"learn":[56.15740098],"iteration":631,"passed_time":4.586855443,"remaining_time":2.67082722},
{"learn":[56.14984857],"iteration":632,"passed_time":4.595855727,"remaining_time":2.664579861},
{"learn":[56.1470584],"iteration":633,"passed_time":4.603006015,"remaining_time":2.657255838},
{"learn":[56.14344547],"iteration":634,"passed_time":4.611171954,"remaining_time":2.650516162},
{"learn":[56.13686932],"iteration":635,"passed_time":4.617361169,"remaining_time":2.642640669},
{"learn":[56.13120505],"iteration":636,"passed_time":4.626013465,"remaining_time":2.636174078},
{"learn":[56.12347641],"iteration":637,"passed_time":4.631725633,"remaining_time":2.628032413},
{"learn":[56.11960859],"iteration":638,"passed_time":4.639796067,"remaining_time":2.621230642},
{"learn":[56.11000217],"iteration":639,"passed_time":4.645724452,"remaining_time":2.613220004},
{"learn":[56.10510737],"iteration":640,"passed_time":4.652613704,"remaining_time":2.605754009},
{"learn":[56.09907699],"iteration":641,"passed_time":4.659855702,"remaining_time":2.598486513},
{"learn":[56.09264298],"iteration":642,"passed_time":4.665812367,"remaining_time":2.590505467},
{"learn":[56.08415809],"iteration":643,"passed_time":4.67365472,"remaining_time":2.583573106},
{"learn":[56.07433616],"iteration":644,"passed_time":4.679517949,"remaining_time":2.575548639},
{"learn":[56.06779996],"iteration":645,"passed_time":4.687182961,"remaining_time":2.568518217},
{"learn":[56.06145069],"iteration":646,"passed_time":4.692851239,"remaining_time":2.560396426},
{"learn":[56.05677878],"iteration":647,"passed_time":4.699320044,"remaining_time":2.552717061},
{"learn":[56.05349354],"iteration":648,"passed_time":4.705236911,"remaining_time":2.544742921},
{"learn":[56.04547911],"iteration":649,"passed_time":4.711269722,"remaining_time":2.536837542},
{"learn":[56.03971906],"iteration":650,"passed_time":4.71745718,"remaining_time":2.529020823},
{"learn":[56.03172195],"iteration":651,"passed_time":4.723113236,"remaining_time":2.52092547},
{"learn":[56.01956779],"iteration":652,"passed_time":4.729225644,"remaining_time":2.513080089},
{"learn":[56.01162862],"iteration":653,"passed_time":4.735650056,"remaining_time":2.505405076},
{"learn":[56.00669576],"iteration":654,"passed_time":4.741538877,"remaining_time":2.497451775},
{"learn":[55.99920085],"iteration":655,"passed_time":4.747880048,"remaining_time":2.489741976},
{"learn":[55.99389284],"iteration":656,"passed_time":4.753789443,"remaining_time":2.481810927},
{"learn":[55.98264203],"iteration":657,"passed_time":4.759047734,"remaining_time":2.473547606},
{"learn":[55.97786338],"iteration":658,"passed_time":4.765227058,"remaining_time":2.465769995},
{"learn":[55.96632399],"iteration":659,"passed_time":4.770809774,"remaining_time":2.457689884},
{"learn":[55.96177182],"iteration":660,"passed_time":4.776298343,"remaining_time":2.449569044},
{"learn":[55.95788877],"iteration":661,"passed_time":4.782666922,"remaining_time":2.441905468},
{"learn":[55.95254727],"iteration":662,"passed_time":4.788652772,"remaining_time":2.434051258},
{"learn":[55.94439],"iteration":663,"passed_time":4.793928685,"remaining_time":2.425843431},
{"learn":[55.9365756],"iteration":664,"passed_time":4.800261382,"remaining_time":2.418176787},
{"learn":[55.92977577],"iteration":665,"passed_time":4.806135297,"remaining_time":2.410284068},
{"learn":[55.92614029],"iteration":666,"passed_time":4.812590064,"remaining_time":2.402687393},
{"learn":[55.92044953],"iteration":667,"passed_time":4.818093271,"remaining_time":2.394621207},
{"learn":[55.91810156],"iteration":668,"passed_time":4.823865642,"remaining_time":2.386695856},
{"learn":[55.91193176],"iteration":669,"passed_time":4.830007486,"remaining_time":2.378958911},
{"learn":[55.90726242],"iteration":670,"passed_time":4.836575494,"remaining_time":2.371435674},
{"learn":[55.90102335],"iteration":671,"passed_time":4.843240231,"remaining_time":2.363962494},
{"learn":[55.89062175],"iteration":672,"passed_time":4.851730097,"remaining_time":2.357378517},
{"learn":[55.88784043],"iteration":673,"passed_time":4.860989869,"remaining_time":2.351161272},
{"learn":[55.88210543],"iteration":674,"passed_time":4.869565536,"remaining_time":2.344605629},
{"learn":[55.87609184],"iteration":675,"passed_time":4.875811991,"remaining_time":2.33692764},
{"learn":[55.87115126],"iteration":676,"passed_time":4.884327967,"remaining_time":2.330336681},
{"learn":[55.86497231],"iteration":677,"passed_time":4.889918734,"remaining_time":2.322350785},
{"learn":[55.85895712],"iteration":678,"passed_time":4.897858427,"remaining_time":2.315482408},
{"learn":[55.85261386],"iteration":679,"passed_time":4.903754309,"remaining_time":2.307649087},
{"learn":[55.84872469],"iteration":680,"passed_time":4.910227726,"remaining_time":2.300091989},
{"learn":[55.83775478],"iteration":681,"passed_time":4.917891939,"remaining_time":2.293093309},
{"learn":[55.83402355],"iteration":682,"passed_time":4.923585666,"remaining_time":2.28517812},
{"learn":[55.82858413],"iteration":683,"passed_time":4.931419649,"remaining_time":2.2782582},
{"learn":[55.8232586],"iteration":684,"passed_time":4.937345108,"remaining_time":2.270457969},
{"learn":[55.81550156],"iteration":685,"passed_time":4.944319892,"remaining_time":2.263143507},
{"learn":[55.80696398],"iteration":686,"passed_time":4.951271681,"remaining_time":2.255819558},
{"learn":[55.79586379],"iteration":687,"passed_time":4.957626332,"remaining_time":2.248225895},
{"learn":[55.79039828],"iteration":688,"passed_time":4.963512288,"remaining_time":2.24042427},
{"learn":[55.7831701],"iteration":689,"passed_time":4.969517579,"remaining_time":2.232681811},
{"learn":[55.77589457],"iteration":690,"passed_time":4.975942565,"remaining_time":2.225132059},
{"learn":[55.76858768],"iteration":691,"passed_time":4.982054289,"remaining_time":2.217446129},
{"learn":[55.76529488],"iteration":692,"passed_time":4.98776973,"remaining_time":2.209589188},
{"learn":[55.75789066],"iteration":693,"passed_time":4.994219944,"remaining_time":2.202062396},
{"learn":[55.75216889],"iteration":694,"passed_time":4.999961499,"remaining_time":2.194227708},
{"learn":[55.74563798],"iteration":695,"passed_time":5.005709126,"remaining_time":2.186401687},
{"learn":[55.73754704],"iteration":696,"passed_time":5.011700579,"remaining_time":2.178687626},
{"learn":[55.7327562],"iteration":697,"passed_time":5.017416749,"remaining_time":2.170859396},
{"learn":[55.7260997],"iteration":698,"passed_time":5.023303812,"remaining_time":2.163110798},
{"learn":[55.71957533],"iteration":699,"passed_time":5.028958081,"remaining_time":2.155267749},
{"learn":[55.70587341],"iteration":700,"passed_time":5.034907781,"remaining_time":2.147556957},
{"learn":[55.69659075],"iteration":701,"passed_time":5.041015852,"remaining_time":2.13991841},
{"learn":[55.69101532],"iteration":702,"passed_time":5.046831433,"remaining_time":2.132160648},
{"learn":[55.68172945],"iteration":703,"passed_time":5.052886696,"remaining_time":2.124509179},
{"learn":[55.67347857],"iteration":704,"passed_time":5.05893544,"remaining_time":2.11685951},
{"learn":[55.66662559],"iteration":705,"passed_time":5.064481902,"remaining_time":2.109005212},
{"learn":[55.65776041],"iteration":706,"passed_time":5.070612316,"remaining_time":2.101399446},
{"learn":[55.65421149],"iteration":707,"passed_time":5.075811663,"remaining_time":2.09341385},
{"learn":[55.64831418],"iteration":708,"passed_time":5.081095177,"remaining_time":2.085470658},
{"learn":[55.62922144],"iteration":709,"passed_time":5.086781478,"remaining_time":2.077699477},
{"learn":[55.6179717],"iteration":710,"passed_time":5.092464824,"remaining_time":2.069932959},
{"learn":[55.61213629],"iteration":711,"passed_time":5.098878112,"remaining_time":2.062467551},
{"learn":[55.59973231],"iteration":712,"passed_time":5.105196203,"remaining_time":2.054966774},
{"learn":[55.59264523],"iteration":713,"passed_time":5.111090693,"remaining_time":2.047299633},
{"learn":[55.58600899],"iteration":714,"passed_time":5.116752113,"remaining_time":2.039544549},
{"learn":[55.57577064],"iteration":715,"passed_time":5.122751713,"remaining_time":2.031929451},
{"learn":[55.56593656],"iteration":716,"passed_time":5.129089246,"remaining_time":2.024452241},
{"learn":[55.5591194],"iteration":717,"passed_time":5.135329889,"remaining_time":2.016940151},
{"learn":[55.55384271],"iteration":718,"passed_time":5.141068275,"remaining_time":2.009235306},
{"learn":[55.54492403],"iteration":719,"passed_time":5.14749925,"remaining_time":2.001805264},
{"learn":[55.5353046],"iteration":720,"passed_time":5.15429399,"remaining_time":1.994518756},
{"learn":[55.532319],"iteration":721,"passed_time":5.161119421,"remaining_time":1.987245428},
{"learn":[55.52728313],"iteration":722,"passed_time":5.168335645,"remaining_time":1.980123062},
{"learn":[55.5196742],"iteration":723,"passed_time":5.175823261,"remaining_time":1.973103895},
{"learn":[55.51318572],"iteration":724,"passed_time":5.183062992,"remaining_time":1.965989411},
{"learn":[55.50499628],"iteration":725,"passed_time":5.190977258,"remaining_time":1.959129158},
{"learn":[55.49790522],"iteration":726,"passed_time":5.198948722,"remaining_time":1.952287484},
{"learn":[55.49073293],"iteration":727,"passed_time":5.206969163,"remaining_time":1.945461006},
{"learn":[55.48459733],"iteration":728,"passed_time":5.215186248,"remaining_time":1.938704353},
{"learn":[55.47784186],"iteration":729,"passed_time":5.224042177,"remaining_time":1.932179983},
{"learn":[55.47189311],"iteration":730,"passed_time":5.23334893,"remaining_time":1.925815133},
{"learn":[55.46916126],"iteration":731,"passed_time":5.24268436,"remaining_time":1.919452744},
{"learn":[55.4620939],"iteration":732,"passed_time":5.252080164,"remaining_time":1.913104234},
{"learn":[55.4559827],"iteration":733,"passed_time":5.26203237,"remaining_time":1.90694906},
{"learn":[55.44752136],"iteration":734,"passed_time":5.27250545,"remaining_time":1.900971353},
{"learn":[55.44222826],"iteration":735,"passed_time":5.283117565,"remaining_time":1.8950313},
{"learn":[55.43045929],"iteration":736,"passed_time":5.292571899,"remaining_time":1.888665413},
{"learn":[55.4238543],"iteration":737,"passed_time":5.302801349,"remaining_time":1.882566332},
{"learn":[55.41610789],"iteration":738,"passed_time":5.312622669,"remaining_time":1.876311931},
{"learn":[55.4105309],"iteration":739,"passed_time":5.322057081,"remaining_time":1.869911947},
{"learn":[55.40222173],"iteration":740,"passed_time":5.331010459,"remaining_time":1.86333564},
{"learn":[55.39599524],"iteration":741,"passed_time":5.339227846,"remaining_time":1.856497014},
{"learn":[55.38853576],"iteration":742,"passed_time":5.347561869,"remaining_time":1.849695021},
{"learn":[55.38251206],"iteration":743,"passed_time":5.355646488,"remaining_time":1.842803093},
{"learn":[55.37466825],"iteration":744,"passed_time":5.363805869,"remaining_time":1.835933552},
{"learn":[55.37044476],"iteration":745,"passed_time":5.371134187,"remaining_time":1.828777592},
{"learn":[55.36186956],"iteration":746,"passed_time":5.378285826,"remaining_time":1.821561331},
{"learn":[55.3532163],"iteration":747,"passed_time":5.385457183,"remaining_time":1.814351885},
{"learn":[55.34544639],"iteration":748,"passed_time":5.39234371,"remaining_time":1.807047091},
{"learn":[55.33757001],"iteration":749,"passed_time":5.398808669,"remaining_time":1.79960289},
{"learn":[55.33012091],"iteration":750,"passed_time":5.405602488,"remaining_time":1.792270332},
{"learn":[55.32178697],"iteration":751,"passed_time":5.41264015,"remaining_time":1.785019624},
{"learn":[55.31817722],"iteration":752,"passed_time":5.419285983,"remaining_time":1.777640953},
{"learn":[55.31133552],"iteration":753,"passed_time":5.424976255,"remaining_time":1.769952465},
{"learn":[55.30884747],"iteration":754,"passed_time":5.430655652,"remaining_time":1.762265741},
{"learn":[55.30216518],"iteration":755,"passed_time":5.43640789,"remaining_time":1.754607838},
{"learn":[55.29337341],"iteration":756,"passed_time":5.442010453,"remaining_time":1.746906922},
{"learn":[55.28369168],"iteration":757,"passed_time":5.447322728,"remaining_time":1.739118866},
{"learn":[55.27773789],"iteration":758,"passed_time":5.452775348,"remaining_time":1.731381896},
{"learn":[55.27172626],"iteration":759,"passed_time":5.457809371,"remaining_time":1.723518749},
{"learn":[55.26763501],"iteration":760,"passed_time":5.463476832,"remaining_time":1.715861975},
{"learn":[55.26098502],"iteration":761,"passed_time":5.469132172,"remaining_time":1.708206636},
{"learn":[55.25298042],"iteration":762,"passed_time":5.475104965,"remaining_time":1.700655146},
{"learn":[55.24414109],"iteration":763,"passed_time":5.480521546,"remaining_time":1.692935975},
{"learn":[55.23782339],"iteration":764,"passed_time":5.485865849,"remaining_time":1.68520062},
{"learn":[55.23081183],"iteration":765,"passed_time":5.492341077,"remaining_time":1.677816987},
{"learn":[55.22374478],"iteration":766,"passed_time":5.498181313,"remaining_time":1.670242824},
{"learn":[55.21863513],"iteration":767,"passed_time":5.504204362,"remaining_time":1.662728401},
{"learn":[55.2125604],"iteration":768,"passed_time":5.509979797,"remaining_time":1.655143476},
{"learn":[55.20737114],"iteration":769,"passed_time":5.515338303,"remaining_time":1.647438714},
{"learn":[55.20274022],"iteration":770,"passed_time":5.521080989,"remaining_time":1.639854146},
{"learn":[55.19840874],"iteration":771,"passed_time":5.527205615,"remaining_time":1.63238715},
{"learn":[55.19493599],"iteration":772,"passed_time":5.533008616,"remaining_time":1.62482918},
{"learn":[55.19109281],"iteration":773,"passed_time":5.539288093,"remaining_time":1.617414869},
{"learn":[55.18809317],"iteration":774,"passed_time":5.545631465,"remaining_time":1.610022038},
{"learn":[55.18195641],"iteration":775,"passed_time":5.551782193,"remaining_time":1.602576303},
{"learn":[55.17276342],"iteration":776,"passed_time":5.558844443,"remaining_time":1.59539551},
{"learn":[55.16703577],"iteration":777,"passed_time":5.565920941,"remaining_time":1.588219086},
{"learn":[55.16356714],"iteration":778,"passed_time":5.572599854,"remaining_time":1.580930125},
{"learn":[55.15212871],"iteration":779,"passed_time":5.579672996,"remaining_time":1.573753922},
{"learn":[55.14739937],"iteration":780,"passed_time":5.587306842,"remaining_time":1.566735209},
{"learn":[55.14141676],"iteration":781,"passed_time":5.594152039,"remaining_time":1.55949507},
{"learn":[55.12741894],"iteration":782,"passed_time":5.601604643,"remaining_time":1.552424275},
{"learn":[55.12058195],"iteration":783,"passed_time":5.608829018,"remaining_time":1.545289627},
{"learn":[55.11667213],"iteration":784,"passed_time":5.616207812,"remaining_time":1.538197044},
{"learn":[55.11389826],"iteration":785,"passed_time":5.624586874,"remaining_time":1.53137607},
{"learn":[55.09911781],"iteration":786,"passed_time":5.633169648,"remaining_time":1.524606271},
{"learn":[55.09430673],"iteration":787,"passed_time":5.640811384,"remaining_time":1.517578697},
{"learn":[55.08813901],"iteration":788,"passed_time":5.648602264,"remaining_time":1.510589452},
{"learn":[55.0839499],"iteration":789,"passed_time":5.656998735,"remaining_time":1.503759158},
{"learn":[55.07471846],"iteration":790,"passed_time":5.665548074,"remaining_time":1.496965294},
{"learn":[55.07175096],"iteration":791,"passed_time":5.674607785,"remaining_time":1.490301034},
{"learn":[55.06442095],"iteration":792,"passed_time":5.684651733,"remaining_time":1.483887653},
{"learn":[55.0575362],"iteration":793,"passed_time":5.694582283,"remaining_time":1.477435706},
{"learn":[55.04808543],"iteration":794,"passed_time":5.705935972,"remaining_time":1.47134198},
{"learn":[55.04428636],"iteration":795,"passed_time":5.716729128,"remaining_time":1.465091384},
{"learn":[55.03926794],"iteration":796,"passed_time":5.727562771,"remaining_time":1.458839702},
{"learn":[55.03383521],"iteration":797,"passed_time":5.740352738,"remaining_time":1.453071746},
{"learn":[55.02614725],"iteration":798,"passed_time":5.752286382,"remaining_time":1.447070792},
{"learn":[55.01633189],"iteration":799,"passed_time":5.763987231,"remaining_time":1.440996808},
{"learn":[55.01046733],"iteration":800,"passed_time":5.776934236,"remaining_time":1.435218368},
{"learn":[55.00433464],"iteration":801,"passed_time":5.78835603,"remaining_time":1.429045504},
{"learn":[54.99884644],"iteration":802,"passed_time":5.798698374,"remaining_time":1.422594744},
{"learn":[54.99470549],"iteration":803,"passed_time":5.808236501,"remaining_time":1.415938251},
{"learn":[54.98886747],"iteration":804,"passed_time":5.818703626,"remaining_time":1.409499636},
{"learn":[54.98549733],"iteration":805,"passed_time":5.827783382,"remaining_time":1.402717092},
{"learn":[54.97652784],"iteration":806,"passed_time":5.836918557,"remaining_time":1.395942109},
{"learn":[54.97075865],"iteration":807,"passed_time":5.845419233,"remaining_time":1.389010511},
{"learn":[54.95693158],"iteration":808,"passed_time":5.853655862,"remaining_time":1.382012694},
{"learn":[54.9480426],"iteration":809,"passed_time":5.862908567,"remaining_time":1.375250158},
{"learn":[54.94267665],"iteration":810,"passed_time":5.872218009,"remaining_time":1.368494703},
{"learn":[54.93671093],"iteration":811,"passed_time":5.880745953,"remaining_time":1.361552019},
{"learn":[54.92931373],"iteration":812,"passed_time":5.89377254,"remaining_time":1.355640178},
{"learn":[54.92537664],"iteration":813,"passed_time":5.905309131,"remaining_time":1.349370391},
{"learn":[54.92060079],"iteration":814,"passed_time":5.911789623,"remaining_time":1.341939976},
{"learn":[54.91088469],"iteration":815,"passed_time":5.9213928,"remaining_time":1.335216023},
{"learn":[54.90609282],"iteration":816,"passed_time":5.928039378,"remaining_time":1.327822774},
{"learn":[54.90344623],"iteration":817,"passed_time":5.936797107,"remaining_time":1.320901068},
{"learn":[54.90073374],"iteration":818,"passed_time":5.942906235,"remaining_time":1.313389534},
{"learn":[54.89244586],"iteration":819,"passed_time":5.952665841,"remaining_time":1.306682746},
{"learn":[54.88445486],"iteration":820,"passed_time":5.960132725,"remaining_time":1.299468645},
{"learn":[54.87687651],"iteration":821,"passed_time":5.968989135,"remaining_time":1.292554825},
{"learn":[54.86882389],"iteration":822,"passed_time":5.975639909,"remaining_time":1.285161924},
{"learn":[54.86362467],"iteration":823,"passed_time":5.982100599,"remaining_time":1.277730225},
{"learn":[54.85396179],"iteration":824,"passed_time":5.988124459,"remaining_time":1.270208219},
{"learn":[54.84957817],"iteration":825,"passed_time":5.995818448,"remaining_time":1.263041658},
{"learn":[54.84858597],"iteration":826,"passed_time":6.002036553,"remaining_time":1.255565083},
{"learn":[54.84266569],"iteration":827,"passed_time":6.007741327,"remaining_time":1.247984913},
{"learn":[54.8386719],"iteration":828,"passed_time":6.013625931,"remaining_time":1.240446362},
{"learn":[54.83270835],"iteration":829,"passed_time":6.019825235,"remaining_time":1.232976253},
{"learn":[54.82977447],"iteration":830,"passed_time":6.025974203,"remaining_time":1.225498966},
{"learn":[54.82569221],"iteration":831,"passed_time":6.03176524,"remaining_time":1.217952597},
{"learn":[54.81985667],"iteration":832,"passed_time":6.041352241,"remaining_time":1.211171458},
{"learn":[54.8160681],"iteration":833,"passed_time":6.050917355,"remaining_time":1.204379234},
{"learn":[54.80522428],"iteration":834,"passed_time":6.058622772,"remaining_time":1.197212883},
{"learn":[54.80334349],"iteration":835,"passed_time":6.066633955,"remaining_time":1.190105226},
{"learn":[54.79749774],"iteration":836,"passed_time":6.073809985,"remaining_time":1.182832769},
{"learn":[54.78832753],"iteration":837,"passed_time":6.082589313,"remaining_time":1.175870488},
{"learn":[54.78241031],"iteration":838,"passed_time":6.089282706,"remaining_time":1.168503594},
{"learn":[54.77631216],"iteration":839,"passed_time":6.097638273,"remaining_time":1.161454909},
{"learn":[54.76970755],"iteration":840,"passed_time":6.103420488,"remaining_time":1.153916597},
{"learn":[54.76562541],"iteration":841,"passed_time":6.111974457,"remaining_time":1.14690257},
{"learn":[54.7625594],"iteration":842,"passed_time":6.117791277,"remaining_time":1.139375125},
{"learn":[54.75824313],"iteration":843,"passed_time":6.12524001,"remaining_time":1.132153367},
{"learn":[54.75118025],"iteration":844,"passed_time":6.133133234,"remaining_time":1.125012605},
{"learn":[54.74508614],"iteration":845,"passed_time":6.13907638,"remaining_time":1.117515086},
{"learn":[54.7303015],"iteration":846,"passed_time":6.147621636,"remaining_time":1.110491275},
{"learn":[54.72102836],"iteration":847,"passed_time":6.153676814,"remaining_time":1.103017542},
{"learn":[54.71860747],"iteration":848,"passed_time":6.161712559,"remaining_time":1.095899407},
{"learn":[54.71312469],"iteration":849,"passed_time":6.168312686,"remaining_time":1.088525768},
{"learn":[54.70387621],"iteration":850,"passed_time":6.176613131,"remaining_time":1.081451653},
{"learn":[54.6973727],"iteration":851,"passed_time":6.18271931,"remaining_time":1.073993495},
{"learn":[54.69164965],"iteration":852,"passed_time":6.189673735,"remaining_time":1.066684688},
{"learn":[54.68651855],"iteration":853,"passed_time":6.197217297,"remaining_time":1.05947743},
{"learn":[54.68312753],"iteration":854,"passed_time":6.203220194,"remaining_time":1.052008103},
{"learn":[54.67792164],"iteration":855,"passed_time":6.211290226,"remaining_time":1.044889945},
{"learn":[54.67447833],"iteration":856,"passed_time":6.217105698,"remaining_time":1.037393366},
{"learn":[54.66759383],"iteration":857,"passed_time":6.224895853,"remaining_time":1.030227519},
{"learn":[54.66030452],"iteration":858,"passed_time":6.231520963,"remaining_time":1.022868982},
{"learn":[54.65415175],"iteration":859,"passed_time":6.239024865,"remaining_time":1.015655211},
{"learn":[54.64857666],"iteration":860,"passed_time":6.246240098,"remaining_time":1.008394162},
{"learn":[54.6424527],"iteration":861,"passed_time":6.253107645,"remaining_time":1.001077558},
{"learn":[54.63898044],"iteration":862,"passed_time":6.260993394,"remaining_time":0.9939236326},
{"learn":[54.63440345],"iteration":863,"passed_time":6.266760314,"remaining_time":0.9864344939},
{"learn":[54.62742435],"iteration":864,"passed_time":6.275294118,"remaining_time":0.9793811629},
{"learn":[54.62047932],"iteration":865,"passed_time":6.281085334,"remaining_time":0.9719000402},
{"learn":[54.61602974],"iteration":866,"passed_time":6.289626169,"remaining_time":0.9648446141},
{"learn":[54.61223312],"iteration":867,"passed_time":6.295965702,"remaining_time":0.9574510054},
{"learn":[54.6017762],"iteration":868,"passed_time":6.304256728,"remaining_time":0.9503540061},
{"learn":[54.59588947],"iteration":869,"passed_time":6.310552665,"remaining_time":0.9429561453},
{"learn":[54.58956246],"iteration":870,"passed_time":6.316672094,"remaining_time":0.9355346729},
{"learn":[54.58390265],"iteration":871,"passed_time":6.324720221,"remaining_time":0.9283992985},
{"learn":[54.57926883],"iteration":872,"passed_time":6.330894772,"remaining_time":0.9209892739},
{"learn":[54.57561174],"iteration":873,"passed_time":6.340374674,"remaining_time":0.9140585915},
{"learn":[54.56611736],"iteration":874,"passed_time":6.346520208,"remaining_time":0.9066457441},
{"learn":[54.55686762],"iteration":875,"passed_time":6.354962288,"remaining_time":0.8995608718},
{"learn":[54.55107377],"iteration":876,"passed_time":6.360899758,"remaining_time":0.8921216308},
{"learn":[54.54505845],"iteration":877,"passed_time":6.367655477,"remaining_time":0.8847995082},
{"learn":[54.54125118],"iteration":878,"passed_time":6.374244662,"remaining_time":0.8774557498},
{"learn":[54.53678453],"iteration":879,"passed_time":6.380370377,"remaining_time":0.870050506},
{"learn":[54.53179663],"iteration":880,"passed_time":6.390083087,"remaining_time":0.8631326758},
{"learn":[54.52333431],"iteration":881,"passed_time":6.395619944,"remaining_time":0.8556498338},
{"learn":[54.51696345],"iteration":882,"passed_time":6.403039451,"remaining_time":0.848420856},
{"learn":[54.51137087],"iteration":883,"passed_time":6.408498271,"remaining_time":0.8409341623},
{"learn":[54.50867021],"iteration":884,"passed_time":6.415481262,"remaining_time":0.8336501074},
{"learn":[54.50373692],"iteration":885,"passed_time":6.422687816,"remaining_time":0.8263954978},
{"learn":[54.50037048],"iteration":886,"passed_time":6.428413809,"remaining_time":0.8189523792},
{"learn":[54.49461771],"iteration":887,"passed_time":6.43609862,"remaining_time":0.8117601863},
{"learn":[54.48874558],"iteration":888,"passed_time":6.441636089,"remaining_time":0.8042987692},
{"learn":[54.48147898],"iteration":889,"passed_time":6.449307456,"remaining_time":0.797105416},
{"learn":[54.47757656],"iteration":890,"passed_time":6.455911058,"remaining_time":0.7897803651},
{"learn":[54.47256226],"iteration":891,"passed_time":6.462448671,"remaining_time":0.7824489422},
{"learn":[54.46699904],"iteration":892,"passed_time":6.470374399,"remaining_time":0.7752856222},
{"learn":[54.46059153],"iteration":893,"passed_time":6.475700747,"remaining_time":0.7678123928},
{"learn":[54.45253394],"iteration":894,"passed_time":6.484551007,"remaining_time":0.7607573807},
{"learn":[54.4478337],"iteration":895,"passed_time":6.490801403,"remaining_time":0.7533965914},
{"learn":[54.44316959],"iteration":896,"passed_time":6.498319194,"remaining_time":0.7461838093},
{"learn":[54.43416706],"iteration":897,"passed_time":6.50511369,"remaining_time":0.7388881919},
{"learn":[54.42928578],"iteration":898,"passed_time":6.511699118,"remaining_time":0.7315702013},
{"learn":[54.4253998],"iteration":899,"passed_time":6.518951278,"remaining_time":0.7243279198},
{"learn":[54.41618313],"iteration":900,"passed_time":6.524905582,"remaining_time":0.7169430106},
{"learn":[54.41476999],"iteration":901,"passed_time":6.532550571,"remaining_time":0.7097449623},
{"learn":[54.40440749],"iteration":902,"passed_time":6.538476072,"remaining_time":0.702361217},
{"learn":[54.39964607],"iteration":903,"passed_time":6.545231391,"remaining_time":0.6950688203},
{"learn":[54.39650958],"iteration":904,"passed_time":6.551881764,"remaining_time":0.687766594},
{"learn":[54.39155455],"iteration":905,"passed_time":6.558006985,"remaining_time":0.6804113207},
{"learn":[54.38497261],"iteration":906,"passed_time":6.566230161,"remaining_time":0.6732738754},
{"learn":[54.37629331],"iteration":907,"passed_time":6.572020492,"remaining_time":0.6658875388},
{"learn":[54.36899582],"iteration":908,"passed_time":6.580256618,"remaining_time":0.6587495624},
{"learn":[54.36223522],"iteration":909,"passed_time":6.587155218,"remaining_time":0.6514768897},
{"learn":[54.35463954],"iteration":910,"passed_time":6.596640328,"remaining_time":0.6444577269},
{"learn":[54.35048094],"iteration":911,"passed_time":6.60319591,"remaining_time":0.6371504825},
{"learn":[54.34653102],"iteration":912,"passed_time":6.611909718,"remaining_time":0.6300505427},
{"learn":[54.34025405],"iteration":913,"passed_time":6.618601998,"remaining_time":0.622756862},
{"learn":[54.33541035],"iteration":914,"passed_time":6.628462921,"remaining_time":0.6157588506},
{"learn":[54.33218751],"iteration":915,"passed_time":6.634778192,"remaining_time":0.6084294412},
{"learn":[54.32410492],"iteration":916,"passed_time":6.642768475,"remaining_time":0.6012538532},
{"learn":[54.31780288],"iteration":917,"passed_time":6.649850346,"remaining_time":0.5939953468},
{"learn":[54.31257646],"iteration":918,"passed_time":6.656261894,"remaining_time":0.586678143},
{"learn":[54.30843711],"iteration":919,"passed_time":6.664461783,"remaining_time":0.579518416},
{"learn":[54.29826317],"iteration":920,"passed_time":6.670333462,"remaining_time":0.5721567247},
{"learn":[54.29261847],"iteration":921,"passed_time":6.677411375,"remaining_time":0.5649003116},
{"learn":[54.28666663],"iteration":922,"passed_time":6.683302168,"remaining_time":0.5575452513},
{"learn":[54.28151408],"iteration":923,"passed_time":6.689745441,"remaining_time":0.5502388025},
{"learn":[54.27340862],"iteration":924,"passed_time":6.695887699,"remaining_time":0.5429098134},
{"learn":[54.2676811],"iteration":925,"passed_time":6.702083311,"remaining_time":0.5355876512},
{"learn":[54.26383471],"iteration":926,"passed_time":6.709180358,"remaining_time":0.5283389063},
{"learn":[54.25477138],"iteration":927,"passed_time":6.715445422,"remaining_time":0.5210259379},
{"learn":[54.24867552],"iteration":928,"passed_time":6.72209191,"remaining_time":0.5137443764},
{"learn":[54.24291771],"iteration":929,"passed_time":6.729343601,"remaining_time":0.5065097334},
{"learn":[54.23620489],"iteration":930,"passed_time":6.736842049,"remaining_time":0.499293342},
{"learn":[54.23356338],"iteration":931,"passed_time":6.743714877,"remaining_time":0.4920306992},
{"learn":[54.22903357],"iteration":932,"passed_time":6.749704672,"remaining_time":0.4847054802},
{"learn":[54.22327362],"iteration":933,"passed_time":6.755957264,"remaining_time":0.477401691},
{"learn":[54.21631995],"iteration":934,"passed_time":6.761963395,"remaining_time":0.4700830167},
{"learn":[54.21055088],"iteration":935,"passed_time":6.769217015,"remaining_time":0.4628524455},
{"learn":[54.20431479],"iteration":936,"passed_time":6.774917174,"remaining_time":0.4555173767},
{"learn":[54.19938587],"iteration":937,"passed_time":6.78040401,"remaining_time":0.4481716936},
{"learn":[54.1907981],"iteration":938,"passed_time":6.786265821,"remaining_time":0.4408543292},
{"learn":[54.18715545],"iteration":939,"passed_time":6.791998123,"remaining_time":0.4335317951},
{"learn":[54.18436151],"iteration":940,"passed_time":6.798133206,"remaining_time":0.4262378949},
{"learn":[54.18043728],"iteration":941,"passed_time":6.804546784,"remaining_time":0.4189636024},
{"learn":[54.17693933],"iteration":942,"passed_time":6.811351549,"remaining_time":0.4117147808},
{"learn":[54.17354221],"iteration":943,"passed_time":6.818011256,"remaining_time":0.4044582949},
{"learn":[54.16763817],"iteration":944,"passed_time":6.824119894,"remaining_time":0.3971709991},
{"learn":[54.16294415],"iteration":945,"passed_time":6.830606292,"remaining_time":0.3899077587},
{"learn":[54.1544602],"iteration":946,"passed_time":6.836877313,"remaining_time":0.3826341052},
{"learn":[54.15112971],"iteration":947,"passed_time":6.843272071,"remaining_time":0.3753693541},
{"learn":[54.14679624],"iteration":948,"passed_time":6.849913287,"remaining_time":0.3681196814},
{"learn":[54.13881091],"iteration":949,"passed_time":6.857492582,"remaining_time":0.3609206622},
{"learn":[54.13627314],"iteration":950,"passed_time":6.865055206,"remaining_time":0.3537199843},
{"learn":[54.12999473],"iteration":951,"passed_time":6.872714013,"remaining_time":0.3465233956},
{"learn":[54.12498911],"iteration":952,"passed_time":6.88039372,"remaining_time":0.3393268676},
{"learn":[54.11793341],"iteration":953,"passed_time":6.888030158,"remaining_time":0.3321272403},
{"learn":[54.11275577],"iteration":954,"passed_time":6.894988476,"remaining_time":0.3248947449},
{"learn":[54.10532285],"iteration":955,"passed_time":6.903512338,"remaining_time":0.3177348775},
{"learn":[54.09489724],"iteration":956,"passed_time":6.911061421,"remaining_time":0.3105283606},
{"learn":[54.08999529],"iteration":957,"passed_time":6.919059158,"remaining_time":0.3033407981},
{"learn":[54.08447145],"iteration":958,"passed_time":6.92692785,"remaining_time":0.296146029},
{"learn":[54.07585887],"iteration":959,"passed_time":6.935061576,"remaining_time":0.288960899},
{"learn":[54.07128682],"iteration":960,"passed_time":6.941950492,"remaining_time":0.281723277},
{"learn":[54.06506186],"iteration":961,"passed_time":6.94925989,"remaining_time":0.2745029894},
{"learn":[54.06163461],"iteration":962,"passed_time":6.95553032,"remaining_time":0.267242598},
{"learn":[54.05677663],"iteration":963,"passed_time":6.962780573,"remaining_time":0.2600208513},
{"learn":[54.05367013],"iteration":964,"passed_time":6.969160453,"remaining_time":0.2527674776},
{"learn":[54.04741252],"iteration":965,"passed_time":6.975818404,"remaining_time":0.2455256995},
{"learn":[54.03922311],"iteration":966,"passed_time":6.982423505,"remaining_time":0.2382833254},
{"learn":[54.03711176],"iteration":967,"passed_time":6.988523548,"remaining_time":0.2310255718},
{"learn":[54.03120695],"iteration":968,"passed_time":6.994956391,"remaining_time":0.2237808546},
{"learn":[54.02857922],"iteration":969,"passed_time":7.000628724,"remaining_time":0.2165142904},
{"learn":[54.02286133],"iteration":970,"passed_time":7.00621963,"remaining_time":0.209248578},
{"learn":[54.0195334],"iteration":971,"passed_time":7.011784032,"remaining_time":0.2019855482},
{"learn":[54.01613317],"iteration":972,"passed_time":7.017672396,"remaining_time":0.1947349997},
{"learn":[54.01167824],"iteration":973,"passed_time":7.023744136,"remaining_time":0.1874921433},
{"learn":[54.00590444],"iteration":974,"passed_time":7.029982965,"remaining_time":0.1802559735},
{"learn":[54.00336579],"iteration":975,"passed_time":7.03562843,"remaining_time":0.1730072565},
{"learn":[53.99964266],"iteration":976,"passed_time":7.042079539,"remaining_time":0.1657807875},
{"learn":[53.99586241],"iteration":977,"passed_time":7.048134918,"remaining_time":0.1585470022},
{"learn":[53.99406897],"iteration":978,"passed_time":7.054127172,"remaining_time":0.1513142703},
{"learn":[53.9890873],"iteration":979,"passed_time":7.061250116,"remaining_time":0.1441071452},
{"learn":[53.98601064],"iteration":980,"passed_time":7.067081032,"remaining_time":0.1368751678},
{"learn":[53.98139359],"iteration":981,"passed_time":7.073443956,"remaining_time":0.1296557955},
{"learn":[53.97437886],"iteration":982,"passed_time":7.079891257,"remaining_time":0.122439625},
{"learn":[53.96732382],"iteration":983,"passed_time":7.085655,"remaining_time":0.1152139024},
{"learn":[53.95727238],"iteration":984,"passed_time":7.090760063,"remaining_time":0.1079811177},
{"learn":[53.95289496],"iteration":985,"passed_time":7.096205356,"remaining_time":0.1007574797},
{"learn":[53.94939187],"iteration":986,"passed_time":7.102451509,"remaining_time":0.09354799354},
{"learn":[53.94793523],"iteration":987,"passed_time":7.108390941,"remaining_time":0.08633673208},
{"learn":[53.94094637],"iteration":988,"passed_time":7.114369015,"remaining_time":0.07912847237},
{"learn":[53.93328828],"iteration":989,"passed_time":7.120522158,"remaining_time":0.07192446624},
{"learn":[53.92494265],"iteration":990,"passed_time":7.126121233,"remaining_time":0.06471754904},
{"learn":[53.92078291],"iteration":991,"passed_time":7.131647463,"remaining_time":0.05751328599},
{"learn":[53.9181598],"iteration":992,"passed_time":7.137197451,"remaining_time":0.05031257015},
{"learn":[53.91117527],"iteration":993,"passed_time":7.142885215,"remaining_time":0.04311600733},
{"learn":[53.90390705],"iteration":994,"passed_time":7.148846173,"remaining_time":0.03592385012},
{"learn":[53.89776382],"iteration":995,"passed_time":7.154283418,"remaining_time":0.02873206192},
{"learn":[53.89214628],"iteration":996,"passed_time":7.160386348,"remaining_time":0.02154579643},
{"learn":[53.88772289],"iteration":997,"passed_time":7.166442773,"remaining_time":0.01436160876},
{"learn":[53.87803849],"iteration":998,"passed_time":7.172446701,"remaining_time":0.007179626328},
{"learn":[53.87336545],"iteration":999,"passed_time":7.178097164,"remaining_time":0}
]}